Workbook

Sheet Resumen
A1: LATAM Social - avance del alcance completo
A2: Cifras al 2026-08-31. El estado de cada actividad se cambia en la hoja «Actividades».
A4: Avance global
A5: Medida | B5: Valor
A6: Avance por numero de actividades | B6: =IFERROR(SUMPRODUCT(Actividades!$H$2:$H$400,Actividades!$I$2:$I$400)/SUM(Actividades!$I$2:$I$400),0)
A7: Avance ponderado por esfuerzo estimado (semanas por ola) | B7: =IFERROR(SUMPRODUCT($B$22:$B$25,$C$22:$C$25)/SUM($C$22:$C$25),0)
A8: Actividades del alcance total | B8: =COUNTA(Actividades!$A$2:$A$400)
A9: Actividades que cuentan en el denominador | B9: =SUM(Actividades!$I$2:$I$400)
A11: Actividades por estado
A12: Estado | B12: Cuantas | C12: % del total
A13: Terminado | B13: =COUNTIF(Actividades!$G$2:$G$400,$A13) | C13: =IFERROR($B13/COUNTA(Actividades!$A$2:$A$400),0)
A14: En curso | B14: =COUNTIF(Actividades!$G$2:$G$400,$A14) | C14: =IFERROR($B14/COUNTA(Actividades!$A$2:$A$400),0)
A15: Pendiente | B15: =COUNTIF(Actividades!$G$2:$G$400,$A15) | C15: =IFERROR($B15/COUNTA(Actividades!$A$2:$A$400),0)
A16: Bloqueado | B16: =COUNTIF(Actividades!$G$2:$G$400,$A16) | C16: =IFERROR($B16/COUNTA(Actividades!$A$2:$A$400),0)
A17: Aplazado | B17: =COUNTIF(Actividades!$G$2:$G$400,$A17) | C17: =IFERROR($B17/COUNTA(Actividades!$A$2:$A$400),0)
A18: No aplica | B18: =COUNTIF(Actividades!$G$2:$G$400,$A18) | C18: =IFERROR($B18/COUNTA(Actividades!$A$2:$A$400),0)
A20: Avance por ola
A21: Ola | B21: Avance | C21: Semanas est. | D21: Actividades | E21: Terminadas
A22: Ola 0 - Fundaciones | B22: =IFERROR(SUMPRODUCT((Actividades!$B$2:$B$400=$A22)*Actividades!$H$2:$H$400*Actividades!$I$2:$I$400)/SUMPRODUCT((Actividades!$B$2:$B$400=$A22)*Actividades!$I$2:$I$400),0) | C22: 8.5 | D22: =COUNTIF(Actividades!$B$2:$B$400,$A22) | E22: =SUMPRODUCT((Actividades!$B$2:$B$400=$A22)*(Actividades!$G$2:$G$400="Terminado"))
A23: Ola 1 - MVP: operar sin Excel | B23: =IFERROR(SUMPRODUCT((Actividades!$B$2:$B$400=$A23)*Actividades!$H$2:$H$400*Actividades!$I$2:$I$400)/SUMPRODUCT((Actividades!$B$2:$B$400=$A23)*Actividades!$I$2:$I$400),0) | C23: 12 | D23: =COUNTIF(Actividades!$B$2:$B$400,$A23) | E23: =SUMPRODUCT((Actividades!$B$2:$B$400=$A23)*(Actividades!$G$2:$G$400="Terminado"))
A24: Ola 2 - Escalar comercialmente | B24: =IFERROR(SUMPRODUCT((Actividades!$B$2:$B$400=$A24)*Actividades!$H$2:$H$400*Actividades!$I$2:$I$400)/SUMPRODUCT((Actividades!$B$2:$B$400=$A24)*Actividades!$I$2:$I$400),0) | C24: 14 | D24: =COUNTIF(Actividades!$B$2:$B$400,$A24) | E24: =SUMPRODUCT((Actividades!$B$2:$B$400=$A24)*(Actividades!$G$2:$G$400="Terminado"))
A25: Ola 3 - Internacionalizar y endurecer | B25: =IFERROR(SUMPRODUCT((Actividades!$B$2:$B$400=$A25)*Actividades!$H$2:$H$400*Actividades!$I$2:$I$400)/SUMPRODUCT((Actividades!$B$2:$B$400=$A25)*Actividades!$I$2:$I$400),0) | C25: 10 | D25: =COUNTIF(Actividades!$B$2:$B$400,$A25) | E25: =SUMPRODUCT((Actividades!$B$2:$B$400=$A25)*(Actividades!$G$2:$G$400="Terminado"))
A27: Avance por fase
A28: Fase | B28: Nombre | C28: Avance | D28: Actividades | E28: Terminadas
A29: F0 | B29: Discovery | C29: =IFERROR(SUMPRODUCT((Actividades!$C$2:$C$400=$A29)*Actividades!$H$2:$H$400*Actividades!$I$2:$I$400)/SUMPRODUCT((Actividades!$C$2:$C$400=$A29)*Actividades!$I$2:$I$400),0) | D29: =COUNTIF(Actividades!$C$2:$C$400,$A29) | E29: =SUMPRODUCT((Actividades!$C$2:$C$400=$A29)*(Actividades!$G$2:$G$400="Terminado"))
A30: F1 | B30: Arquitectura y esqueleto | C30: =IFERROR(SUMPRODUCT((Actividades!$C$2:$C$400=$A30)*Actividades!$H$2:$H$400*Actividades!$I$2:$I$400)/SUMPRODUCT((Actividades!$C$2:$C$400=$A30)*Actividades!$I$2:$I$400),0) | D30: =COUNTIF(Actividades!$C$2:$C$400,$A30) | E30: =SUMPRODUCT((Actividades!$C$2:$C$400=$A30)*(Actividades!$G$2:$G$400="Terminado"))
A31: F2 | B31: Modelo de datos | C31: =IFERROR(SUMPRODUCT((Actividades!$C$2:$C$400=$A31)*Actividades!$H$2:$H$400*Actividades!$I$2:$I$400)/SUMPRODUCT((Actividades!$C$2:$C$400=$A31)*Actividades!$I$2:$I$400),0) | D31: =COUNTIF(Actividades!$C$2:$C$400,$A31) | E31: =SUMPRODUCT((Actividades!$C$2:$C$400=$A31)*(Actividades!$G$2:$G$400="Terminado"))
A32: F3 | B32: Design System y UX | C32: =IFERROR(SUMPRODUCT((Actividades!$C$2:$C$400=$A32)*Actividades!$H$2:$H$400*Actividades!$I$2:$I$400)/SUMPRODUCT((Actividades!$C$2:$C$400=$A32)*Actividades!$I$2:$I$400),0) | D32: =COUNTIF(Actividades!$C$2:$C$400,$A32) | E32: =SUMPRODUCT((Actividades!$C$2:$C$400=$A32)*(Actividades!$G$2:$G$400="Terminado"))
A33: F4 | B33: Core tecnico | C33: =IFERROR(SUMPRODUCT((Actividades!$C$2:$C$400=$A33)*Actividades!$H$2:$H$400*Actividades!$I$2:$I$400)/SUMPRODUCT((Actividades!$C$2:$C$400=$A33)*Actividades!$I$2:$I$400),0) | D33: =COUNTIF(Actividades!$C$2:$C$400,$A33) | E33: =SUMPRODUCT((Actividades!$C$2:$C$400=$A33)*(Actividades!$G$2:$G$400="Terminado"))
A34: F5 | B34: Adquisicion de creadores | C34: =IFERROR(SUMPRODUCT((Actividades!$C$2:$C$400=$A34)*Actividades!$H$2:$H$400*Actividades!$I$2:$I$400)/SUMPRODUCT((Actividades!$C$2:$C$400=$A34)*Actividades!$I$2:$I$400),0) | D34: =COUNTIF(Actividades!$C$2:$C$400,$A34) | E34: =SUMPRODUCT((Actividades!$C$2:$C$400=$A34)*(Actividades!$G$2:$G$400="Terminado"))
A35: F6 | B35: Portal del creador | C35: =IFERROR(SUMPRODUCT((Actividades!$C$2:$C$400=$A35)*Actividades!$H$2:$H$400*Actividades!$I$2:$I$400)/SUMPRODUCT((Actividades!$C$2:$C$400=$A35)*Actividades!$I$2:$I$400),0) | D35: =COUNTIF(Actividades!$C$2:$C$400,$A35) | E35: =SUMPRODUCT((Actividades!$C$2:$C$400=$A35)*(Actividades!$G$2:$G$400="Terminado"))
A36: F7 | B36: Motor de campana | C36: =IFERROR(SUMPRODUCT((Actividades!$C$2:$C$400=$A36)*Actividades!$H$2:$H$400*Actividades!$I$2:$I$400)/SUMPRODUCT((Actividades!$C$2:$C$400=$A36)*Actividades!$I$2:$I$400),0) | D36: =COUNTIF(Actividades!$C$2:$C$400,$A36) | E36: =SUMPRODUCT((Actividades!$C$2:$C$400=$A36)*(Actividades!$G$2:$G$400="Terminado"))
A37: F8 | B37: Contenido, revision y evidencia | C37: =IFERROR(SUMPRODUCT((Actividades!$C$2:$C$400=$A37)*Actividades!$H$2:$H$400*Actividades!$I$2:$I$400)/SUMPRODUCT((Actividades!$C$2:$C$400=$A37)*Actividades!$I$2:$I$400),0) | D37: =COUNTIF(Actividades!$C$2:$C$400,$A37) | E37: =SUMPRODUCT((Actividades!$C$2:$C$400=$A37)*(Actividades!$G$2:$G$400="Terminado"))
A38: F9 | B38: Finanzas | C38: =IFERROR(SUMPRODUCT((Actividades!$C$2:$C$400=$A38)*Actividades!$H$2:$H$400*Actividades!$I$2:$I$400)/SUMPRODUCT((Actividades!$C$2:$C$400=$A38)*Actividades!$I$2:$I$400),0) | D38: =COUNTIF(Actividades!$C$2:$C$400,$A38) | E38: =SUMPRODUCT((Actividades!$C$2:$C$400=$A38)*(Actividades!$G$2:$G$400="Terminado"))
A39: F10 | B39: Medicion y reportes | C39: =IFERROR(SUMPRODUCT((Actividades!$C$2:$C$400=$A39)*Actividades!$H$2:$H$400*Actividades!$I$2:$I$400)/SUMPRODUCT((Actividades!$C$2:$C$400=$A39)*Actividades!$I$2:$I$400),0) | D39: =COUNTIF(Actividades!$C$2:$C$400,$A39) | E39: =SUMPRODUCT((Actividades!$C$2:$C$400=$A39)*(Actividades!$G$2:$G$400="Terminado"))
A40: F11 | B40: Adquisicion de marcas y CRM | C40: =IFERROR(SUMPRODUCT((Actividades!$C$2:$C$400=$A40)*Actividades!$H$2:$H$400*Actividades!$I$2:$I$400)/SUMPRODUCT((Actividades!$C$2:$C$400=$A40)*Actividades!$I$2:$I$400),0) | D40: =COUNTIF(Actividades!$C$2:$C$400,$A40) | E40: =SUMPRODUCT((Actividades!$C$2:$C$400=$A40)*(Actividades!$G$2:$G$400="Terminado"))
... A46: F17 | B46: Produccion | C46: =IFERROR(SUMPRODUCT((Actividades!$C$2:$C$400=$A46)*Actividades!$H$2:$H$400*Actividades!$I$2:$I$400)/SUMPRODUCT((Actividades!$C$2:$C$400=$A46)*Actividades!$I$2:$I$400),0) | D46: =COUNTIF(Actividades!$C$2:$C$400,$A46) | E46: =SUMPRODUCT((Actividades!$C$2:$C$400=$A46)*(Actividades!$G$2:$G$400="Terminado"))
A48: Como leer esto
A49: - El primer numero cuenta ACTIVIDADES, no semanas. Las que quedan son de media mas grandes que las hechas: finanzas, integraciones y los dos portales son fases enteras sin empezar.
A50: - El segundo numero pondera cada ola por su estimacion de esfuerzo del propio roadmap, y es el mas honesto de los dos.
A51: - Ninguno de los dos incluye el trabajo de endurecimiento que se ha hecho de mas (compilador de restricciones, compilador de periodos, seis puertas de calidad, bateria de 940 aserciones de restriccion). Ese trabajo no es una actividad del roadmap: es lo que hace que las que si lo son no haya que rehacerlas.
A52: - «En curso» cuenta como medio. Si prefiere una lectura conservadora, ponga el peso de «En curso» a 0% en la hoja Config y todo se recalcula.
A53: - Para cambiar un estado: hoja «Actividades», columna Estado, lista desplegable. No toque las columnas Avance ni Cuenta: son formulas.
A54: - La numeracion de F9 se reordeno al ejecutar: la fila «9.2» de esta hoja es la iteracion 9.3 del roadmap, y asi las siguientes. La nota de cada fila lo dice.
A55: - Las filas marcadas «FUERA DEL ALCANCE ORIGINAL» son iteraciones que no estaban en el plan y se hicieron porque el trabajo las destapo. Cuentan en el total.
A57: Tareas, preguntas y decisiones
A58: Que se mira | B58: Abiertas | C58: Total
A59: Tareas (hoja «Tareas») | B59: =COUNTIF(Tareas!$B$3:$B$65,"Abierta") | C59: 63
A60: Preguntas de negocio (hoja «Preguntas») | B60: =COUNTIF(Preguntas!$B$3:$B$60,"Abierta") | C60: 58
A61: De ellas, críticas y sin respuesta | B61: =COUNTIFS(Preguntas!$B$3:$B$60,"Abierta",Preguntas!$C$3:$C$60,"Critica")+COUNTIFS(Tareas!$B$3:$B$65,"Abierta",Tareas!$C$3:$C$65,"Critica")
A62: Decisiones sin firma formal (hoja «Decisiones») | B62: =COUNTIF(Decisiones!$B$3:$B$201,"Propuesta") | C62: 199
A64: - Una pregunta abierta no es una duda: es trabajo parado. Una decisión «Propuesta» está construida y funcionando, y lo que le falta es tu confirmación explícita.
A65: Tareas y preguntas abiertas
A66: Que se mira | B66: Abiertas | C66: Total
A67: Tareas (hoja «Tareas») | B67: =COUNTIF(Tareas!$B$3:$B$62,"Abierta") | C67: 60
A68: Preguntas de negocio (hoja «Preguntas») | B68: =COUNTIF(Preguntas!$B$3:$B$60,"Abierta") | C68: 58
A69: De ellas, criticas (rojas) y sin respuesta | B69: =COUNTIFS(Preguntas!$B$3:$B$60,"Abierta",Preguntas!$C$3:$C$60,"Critica")+COUNTIFS(Tareas!$B$3:$B$62,"Abierta",Tareas!$C$3:$C$62,"Critica")
A71: - Una pregunta abierta no es una duda: es trabajo parado. Q-40 (tu contador) para las retenciones, Q-44 (tu contador) la facturacion, T-09 (tu abogado) toda activacion de creadores.

Sheet Config
A1: Estados y su peso en el avance
A2: Estado | B2: Peso | C2: Cuenta en el total | D2: Que significa
A3: Terminado | B3: 1 | C3: 1 | D3: Entregado, verificado y con su documento de iteracion cerrado.
A4: En curso | B4: 0.5 | C4: 1 | D4: Hay trabajo hecho y demostrable, pero la actividad no esta completa. Cuenta como medio.
A5: Pendiente | B5: 0 | C5: 1 | D5: No empezada.
A6: Bloqueado | B6: 0 | C6: 1 | D6: No se puede avanzar sin una decision externa (contador, abogado, proveedor).
A7: Aplazado | B7: 0 | C7: 0 | D7: Movida a proposito a otro momento del plan. NO cuenta en el denominador para no contarla dos veces.
A8: No aplica | B8: 0 | C8: 0 | D8: Descartada del alcance. No cuenta en el denominador.
A11: Esfuerzo estimado por ola (docs/04-ROADMAP, punto medio del rango)
A12: Ola | B12: Semanas | C12: Rango original
A13: Ola 0 - Fundaciones | B13: 8.5 | C13: 7 a 10 semanas
A14: Ola 1 - MVP: operar sin Excel | B14: 12 | C14: 10 a 14 semanas
A15: Ola 2 - Escalar comercialmente | B15: 14 | C15: 12 a 16 semanas
A16: Ola 3 - Internacionalizar y endurecer | B16: 10 | C16: 8 a 12 semanas
A19: Estas semanas son para 2 desarrolladores a tiempo completo. Con 1 solo, el propio roadmap dice que hay que multiplicar por 1,7.

Sheet Actividades
A1: ID | B1: Ola | C1: Fase | D1: Nombre de fase | E1: It. | F1: Actividad | G1: Estado | H1: Avance | I1: Cuenta | J1: Notas y evidencia
A2: 1 | B2: Ola 0 - Fundaciones | C2: F0 | D2: Discovery | E2: 0.1 | F2: Definicion de producto, actores, dominios, modulos, procesos, arquitectura, roadmap, decision log, business rules, DoD | G2: Terminado | H2: =IFERROR(INDEX(Config!$B$3:$B$8,MATCH($G2,Config!$A$3:$A$8,0)),0) | I2: =IFERROR(INDEX(Config!$C$3:$C$8,MATCH($G2,Config!$A$3:$A$8,0)),0) | J2: 18 documentos en docs/. DEC-001 a DEC-098 registradas
A3: 2 | B3: Ola 0 - Fundaciones | C3: F1 | D3: Arquitectura y esqueleto | E3: 1.1 | F3: Stack, hosting y proveedores definitivos (SMTP, storage, error tracking) | G3: En curso | H3: =IFERROR(INDEX(Config!$B$3:$B$8,MATCH($G3,Config!$A$3:$A$8,0)),0) | I3: =IFERROR(INDEX(Config!$C$3:$C$8,MATCH($G3,Config!$A$3:$A$8,0)),0) | J3: Stack cerrado (Laravel 12 / PHP 8.3 / MySQL-Percona). Hosting: solicitud redactada en tools/solicitud-hosting-mysql8.md, sin contratar. SMTP, S3 y error tracking sin proveedor
A4: 3 | B4: Ola 0 - Fundaciones | C4: F1 | D4: Arquitectura y esqueleto | E4: 1.2 | F4: Esqueleto del proyecto, estructura de modulos, Composer, .env.example | G4: Terminado | H4: =IFERROR(INDEX(Config!$B$3:$B$8,MATCH($G4,Config!$A$3:$A$8,0)),0) | I4: =IFERROR(INDEX(Config!$C$3:$C$8,MATCH($G4,Config!$A$3:$A$8,0)),0) | J4: 13 contextos + Shared. .env.example en el repo
A5: 4 | B5: Ola 0 - Fundaciones | C5: F1 | D5: Arquitectura y esqueleto | E5: 1.3 | F5: CI: lint, analisis estatico, pruebas, Deptrac (fronteras de modulos) | G5: Terminado | H5: =IFERROR(INDEX(Config!$B$3:$B$8,MATCH($G5,Config!$A$3:$A$8,0)),0) | I5: =IFERROR(INDEX(Config!$C$3:$C$8,MATCH($G5,Config!$A$3:$A$8,0)),0) | J5: Seis puertas en verde: Pint, PHPStan, Deptrac, PHPUnit, vigencias, nombres entre capas. .github/workflows/ci.yml
A6: 5 | B6: Ola 0 - Fundaciones | C6: F1 | D6: Arquitectura y esqueleto | E6: 1.4 | F6: Convenciones: naming, commits, ramas, PR template, ADRs | G6: Terminado | H6: =IFERROR(INDEX(Config!$B$3:$B$8,MATCH($G6,Config!$A$3:$A$8,0)),0) | I6: =IFERROR(INDEX(Config!$C$3:$C$8,MATCH($G6,Config!$A$3:$A$8,0)),0) | J6: CONTRIBUTING.md + docs/03-ARCHITECTURE.md. Las decisiones van al DECISION LOG (DEC-nnn), no a ADRs sueltos
A7: 6 | B7: Ola 0 - Fundaciones | C7: F2 | D7: Modelo de datos | E7: 2.1 | F7: Entidades y glosario de negocio | G7: Terminado | H7: =IFERROR(INDEX(Config!$B$3:$B$8,MATCH($G7,Config!$A$3:$A$8,0)),0) | I7: =IFERROR(INDEX(Config!$C$3:$C$8,MATCH($G7,Config!$A$3:$A$8,0)),0) | J7: docs/fase-2/2.1
A8: 7 | B8: Ola 0 - Fundaciones | C8: F2 | D8: Modelo de datos | E8: 2.2 | F8: Relaciones y cardinalidades | G8: Terminado | H8: =IFERROR(INDEX(Config!$B$3:$B$8,MATCH($G8,Config!$A$3:$A$8,0)),0) | I8: =IFERROR(INDEX(Config!$C$3:$C$8,MATCH($G8,Config!$A$3:$A$8,0)),0) | J8: docs/fase-2/2.2
A9: 8 | B9: Ola 0 - Fundaciones | C9: F2 | D9: Modelo de datos | E9: 2.3 | F9: Normalizacion y separacion aplicacion/creador, cliente/marca/contacto | G9: Terminado | H9: =IFERROR(INDEX(Config!$B$3:$B$8,MATCH($G9,Config!$A$3:$A$8,0)),0) | I9: =IFERROR(INDEX(Config!$C$3:$C$8,MATCH($G9,Config!$A$3:$A$8,0)),0) | J9: docs/fase-2/2.3. Incluye N-03, implementada en 7.3
A10: 9 | B10: Ola 0 - Fundaciones | C10: F2 | D10: Modelo de datos | E10: 2.4 | F10: Estados, transiciones e historicos | G10: Terminado | H10: =IFERROR(INDEX(Config!$B$3:$B$8,MATCH($G10,Config!$A$3:$A$8,0)),0) | I10: =IFERROR(INDEX(Config!$C$3:$C$8,MATCH($G10,Config!$A$3:$A$8,0)),0) | J10: docs/fase-2/2.4 y 2.5. Tabla status_transitions + maquinas de estado en codigo
A11: 10 | B11: Ola 0 - Fundaciones | C11: F2 | D11: Modelo de datos | E11: 2.5 | F11: Finanzas: ledger, monedas, impuestos, retenciones, facturacion | G11: Terminado | H11: =IFERROR(INDEX(Config!$B$3:$B$8,MATCH($G11,Config!$A$3:$A$8,0)),0) | I11: =IFERROR(INDEX(Config!$C$3:$C$8,MATCH($G11,Config!$A$3:$A$8,0)),0) | J11: docs/fase-2/2.13 y 2.15. DISENO cerrado; la construccion es F9
A12: 11 | B12: Ola 0 - Fundaciones | C12: F2 | D12: Modelo de datos | E12: 2.6 | F12: Multi-entidad legal: marcas de plataforma, entidades legales, cobertura con vigencia, series, cuentas | G12: Terminado | H12: =IFERROR(INDEX(Config!$B$3:$B$8,MATCH($G12,Config!$A$3:$A$8,0)),0) | I12: =IFERROR(INDEX(Config!$C$3:$C$8,MATCH($G12,Config!$A$3:$A$8,0)),0) | J12: docs/fase-2/2.10. Construido en 4.5b
A13: 12 | B13: Ola 0 - Fundaciones | C13: F2 | D13: Modelo de datos | E13: 2.7 | F13: Integraciones: proveedores, conexiones, asignaciones con vigencia, credenciales, webhooks, trazas | G13: Pendiente | H13: =IFERROR(INDEX(Config!$B$3:$B$8,MATCH($G13,Config!$A$3:$A$8,0)),0) | I13: =IFERROR(INDEX(Config!$C$3:$C$8,MATCH($G13,Config!$A$3:$A$8,0)),0) | J13: Sin documento y sin tablas integration_*. Bloquea F4.6b y toda la F12
... A17: 16 | B17: Ola 0 - Fundaciones | C17: F2 | D17: Modelo de datos | E17: 2.11 | F17: Revision adversarial del modelo + ERD final | G17: Terminado | H17: =IFERROR(INDEX(Config!$B$3:$B$8,MATCH($G17,Config!$A$3:$A$8,0)),0) | I17: =IFERROR(INDEX(Config!$C$3:$C$8,MATCH($G17,Config!$A$3:$A$8,0)),0) | J17: Hecha. Dejo siete hallazgos, los siete cerrados (el ultimo, T-23). Falta publicar el ERD como imagen
A18: 17 | B18: Ola 0 - Fundaciones | C18: F3 | D18: Design System y UX | E18: 3.1 | F18: Journeys de los 6 perfiles | G18: Pendiente | H18: =IFERROR(INDEX(Config!$B$3:$B$8,MATCH($G18,Config!$A$3:$A$8,0)),0) | I18: =IFERROR(INDEX(Config!$C$3:$C$8,MATCH($G18,Config!$A$3:$A$8,0)),0)
A19: 18 | B19: Ola 0 - Fundaciones | C19: F3 | D19: Design System y UX | E19: 3.2 | F19: Tokens: color, tipografia, espaciado, radios, sombras, modo claro/oscuro | G19: Terminado | H19: =IFERROR(INDEX(Config!$B$3:$B$8,MATCH($G19,Config!$A$3:$A$8,0)),0) | I19: =IFERROR(INDEX(Config!$C$3:$C$8,MATCH($G19,Config!$A$3:$A$8,0)),0) | J19: Q-29/Q-30 respondidas (2026-08-30): la identidad visual se configura desde el admin (9.17). El kit de marca esta en marca/, pero el wordmark usa una tipografia de sistema y no una de diseno (T-71): en cuanto haya uno de verdad se sube desde la pantalla.
A20: 19 | B20: Ola 0 - Fundaciones | C20: F3 | D20: Design System y UX | E20: 3.3 | F20: Componentes base: botones, formularios, tablas, cards, badges, modales, tabs, alertas | G20: En curso | H20: =IFERROR(INDEX(Config!$B$3:$B$8,MATCH($G20,Config!$A$3:$A$8,0)),0) | I20: =IFERROR(INDEX(Config!$C$3:$C$8,MATCH($G20,Config!$A$3:$A$8,0)),0) | J20: Existen de facto en las plantillas del panel, sin catalogo ni documentacion
A21: 20 | B21: Ola 0 - Fundaciones | C21: F3 | D21: Design System y UX | E21: 3.4 | F21: Estados: vacio, carga, error, sin permisos, sin resultados | G21: En curso | H21: =IFERROR(INDEX(Config!$B$3:$B$8,MATCH($G21,Config!$A$3:$A$8,0)),0) | I21: =IFERROR(INDEX(Config!$C$3:$C$8,MATCH($G21,Config!$A$3:$A$8,0)),0) | J21: Vacio y sin permisos si (403 con motivo). Carga y error no estan sistematizados
A22: 21 | B22: Ola 0 - Fundaciones | C22: F3 | D22: Design System y UX | E22: 3.5 | F22: Wireframes de baja fidelidad de las 12 pantallas criticas | G22: Pendiente | H22: =IFERROR(INDEX(Config!$B$3:$B$8,MATCH($G22,Config!$A$3:$A$8,0)),0) | I22: =IFERROR(INDEX(Config!$C$3:$C$8,MATCH($G22,Config!$A$3:$A$8,0)),0) | J22: Se ha ido construyendo pantalla a pantalla sin wireframe previo
A23: 22 | B23: Ola 0 - Fundaciones | C23: F3 | D23: Design System y UX | E23: 3.6 | F23: Identidad diferenciada por portal | G23: Terminado | H23: =IFERROR(INDEX(Config!$B$3:$B$8,MATCH($G23,Config!$A$3:$A$8,0)),0) | I23: =IFERROR(INDEX(Config!$C$3:$C$8,MATCH($G23,Config!$A$3:$A$8,0)),0) | J23: Token de densidad por portal en design/tokens.css
A24: 23 | B24: Ola 0 - Fundaciones | C24: F3 | D24: Design System y UX | E24: 3.7 | F24: Sustituir assets del kit por los corregidos y publicar la guia de marca interna | G24: Pendiente | H24: =IFERROR(INDEX(Config!$B$3:$B$8,MATCH($G24,Config!$A$3:$A$8,0)),0) | I24: =IFERROR(INDEX(Config!$C$3:$C$8,MATCH($G24,Config!$A$3:$A$8,0)),0) | J24: Depende de Q-30 y Q-31
A25: 24 | B25: Ola 0 - Fundaciones | C25: F4 | D25: Core tecnico | E25: 4.1 | F25: Identidad: usuarios, login, logout, recuperacion, verificacion de email, sesiones | G25: Terminado | H25: =IFERROR(INDEX(Config!$B$3:$B$8,MATCH($G25,Config!$A$3:$A$8,0)),0) | I25: =IFERROR(INDEX(Config!$C$3:$C$8,MATCH($G25,Config!$A$3:$A$8,0)),0) | J25: docs/fase-5/5.9 y docs/fase-7/7.6b. DEC-113 a DEC-118 y DEC-126. Recuperacion por enlace, misma respuesta exista o no el correo, URL sin token. Desde 7.6b tampoco se teclea la del equipo (BR-SEC-004 cerrada). Falta la verificacion de correo
A26: 25 | B26: Ola 0 - Fundaciones | C26: F4 | D26: Core tecnico | E26: 4.2 | F26: RBAC: roles, permisos, politicas de recurso, pruebas de autorizacion negativas | G26: Terminado | H26: =IFERROR(INDEX(Config!$B$3:$B$8,MATCH($G26,Config!$A$3:$A$8,0)),0) | I26: =IFERROR(INDEX(Config!$C$3:$C$8,MATCH($G26,Config!$A$3:$A$8,0)),0) | J26: docs/fase-3/3.1. 127 permisos usados, todos existentes (puerta de nombres entre capas)
A27: 26 | B27: Ola 0 - Fundaciones | C27: F4 | D27: Core tecnico | E27: 4.3 | F27: Ambito de acceso externo: client_organization_id y creator_id por politica de recurso | G27: Pendiente | H27: =IFERROR(INDEX(Config!$B$3:$B$8,MATCH($G27,Config!$A$3:$A$8,0)),0) | I27: =IFERROR(INDEX(Config!$C$3:$C$8,MATCH($G27,Config!$A$3:$A$8,0)),0) | J27: No hay portales externos todavia. Llega con F6 y F13
A28: 27 | B28: Ola 0 - Fundaciones | C28: F4 | D28: Core tecnico | E28: 4.3b | F28: MFA/TOTP obligatorio para roles con permisos financieros (BR-SEC-005) | G28: Pendiente | H28: =IFERROR(INDEX(Config!$B$3:$B$8,MATCH($G28,Config!$A$3:$A$8,0)),0) | I28: =IFERROR(INDEX(Config!$C$3:$C$8,MATCH($G28,Config!$A$3:$A$8,0)),0) | J28: Barato ahora, caro de retrofitear. Deberia entrar antes de F9
A29: 28 | B29: Ola 0 - Fundaciones | C29: F4 | D29: Core tecnico | E29: 4.4 | F29: Auditoria append-only + activity log, con request_id | G29: Terminado | H29: =IFERROR(INDEX(Config!$B$3:$B$8,MATCH($G29,Config!$A$3:$A$8,0)),0) | I29: =IFERROR(INDEX(Config!$C$3:$C$8,MATCH($G29,Config!$A$3:$A$8,0)),0) | J29: docs/fase-3/3.2 y 3.3. Protegida por dos usuarios de base de datos (DEC-085): falta ejecutar los GRANT en produccion
A30: 29 | B30: Ola 0 - Fundaciones | C30: F4 | D30: Core tecnico | E30: 4.5 | F30: Catalogos maestros + seeders (paises, monedas, idiomas, redes, tipos de documento) | G30: Terminado | H30: =IFERROR(INDEX(Config!$B$3:$B$8,MATCH($G30,Config!$A$3:$A$8,0)),0) | I30: =IFERROR(INDEX(Config!$C$3:$C$8,MATCH($G30,Config!$A$3:$A$8,0)),0) | J30: CimientosSeeder + pantalla de catalogos
... A39: 38 | B39: Ola 0 - Fundaciones | C39: F4 | D39: Core tecnico | E39: 4.12 | F39: Layout de admin, navegacion, busqueda basica, tabla estandar con filtros/orden/paginacion | G39: Terminado | H39: =IFERROR(INDEX(Config!$B$3:$B$8,MATCH($G39,Config!$A$3:$A$8,0)),0) | I39: =IFERROR(INDEX(Config!$C$3:$C$8,MATCH($G39,Config!$A$3:$A$8,0)),0) | J39: layouts/panel + 21 plantillas. La busqueda global no existe; los listados filtran
A40: 39 | B40: Ola 0 - Fundaciones | C40: F4 | D40: Core tecnico | E40: 4.13 | F40: QA de fase + Phase Review Report | G40: Pendiente | H40: =IFERROR(INDEX(Config!$B$3:$B$8,MATCH($G40,Config!$A$3:$A$8,0)),0) | I40: =IFERROR(INDEX(Config!$C$3:$C$8,MATCH($G40,Config!$A$3:$A$8,0)),0)
A41: 40 | B41: Ola 1 - MVP: operar sin Excel | C41: F5 | D41: Adquisicion de creadores | E41: 5.1 | F41: Landing de creadores (responsive, SEO, consentimientos) | G41: Pendiente | H41: =IFERROR(INDEX(Config!$B$3:$B$8,MATCH($G41,Config!$A$3:$A$8,0)),0) | I41: =IFERROR(INDEX(Config!$C$3:$C$8,MATCH($G41,Config!$A$3:$A$8,0)),0) | J41: No hay ninguna ruta publica
A42: 41 | B42: Ola 1 - MVP: operar sin Excel | C42: F5 | D42: Adquisicion de creadores | E42: 5.2 | F42: Formulario de aplicacion multi-paso con guardado parcial | G42: Pendiente | H42: =IFERROR(INDEX(Config!$B$3:$B$8,MATCH($G42,Config!$A$3:$A$8,0)),0) | I42: =IFERROR(INDEX(Config!$C$3:$C$8,MATCH($G42,Config!$A$3:$A$8,0)),0) | J42: La tabla creator_applications existe; el formulario publico no
A43: 42 | B43: Ola 1 - MVP: operar sin Excel | C43: F5 | D43: Adquisicion de creadores | E43: 5.3 | F43: Cuentas sociales declaradas + metricas + evidencias | G43: Terminado | H43: =IFERROR(INDEX(Config!$B$3:$B$8,MATCH($G43,Config!$A$3:$A$8,0)),0) | I43: =IFERROR(INDEX(Config!$C$3:$C$8,MATCH($G43,Config!$A$3:$A$8,0)),0) | J43: docs/fase-3/3.7. Con verificacion y snapshots de metricas
A44: 43 | B44: Ola 1 - MVP: operar sin Excel | C44: F5 | D44: Adquisicion de creadores | E44: 5.4 | F44: Subida de archivos y capturas de insights | G44: En curso | H44: =IFERROR(INDEX(Config!$B$3:$B$8,MATCH($G44,Config!$A$3:$A$8,0)),0) | I44: =IFERROR(INDEX(Config!$C$3:$C$8,MATCH($G44,Config!$A$3:$A$8,0)),0) | J44: La subida existe para identidad; falta el flujo de insights de redes
A45: 44 | B45: Ola 1 - MVP: operar sin Excel | C45: F5 | D45: Adquisicion de creadores | E45: 5.5 | F45: Deteccion de duplicados y validaciones anti-basura (honeypot, rate limit, verificacion de email) | G45: En curso | H45: =IFERROR(INDEX(Config!$B$3:$B$8,MATCH($G45,Config!$A$3:$A$8,0)),0) | I45: =IFERROR(INDEX(Config!$C$3:$C$8,MATCH($G45,Config!$A$3:$A$8,0)),0) | J45: Duplicados: huellas de cuenta de pago con convergencia (4.10). Anti-basura publico: no, porque no hay formulario publico
A46: 45 | B46: Ola 1 - MVP: operar sin Excel | C46: F5 | D46: Adquisicion de creadores | E46: 5.6 | F46: Importacion masiva CSV/Excel con mapeo, previsualizacion, validacion, resumen y reversion | G46: En curso | H46: =IFERROR(INDEX(Config!$B$3:$B$8,MATCH($G46,Config!$A$3:$A$8,0)),0) | I46: =IFERROR(INDEX(Config!$C$3:$C$8,MATCH($G46,Config!$A$3:$A$8,0)),0) | J46: Plantilla CSV y guia escritas (tools/). El importador no esta construido
A47: 46 | B47: Ola 1 - MVP: operar sin Excel | C47: F5 | D47: Adquisicion de creadores | E47: 5.7 | F47: Bandeja de revision + ficha 360 + notas internas | G47: Terminado | H47: =IFERROR(INDEX(Config!$B$3:$B$8,MATCH($G47,Config!$A$3:$A$8,0)),0) | I47: =IFERROR(INDEX(Config!$C$3:$C$8,MATCH($G47,Config!$A$3:$A$8,0)),0) | J47: docs/fase-3/3.4. Rutas solicitudes.* y creadores.show
A48: 47 | B48: Ola 1 - MVP: operar sin Excel | C48: F5 | D48: Adquisicion de creadores | E48: 5.8 | F48: Maquina de estados + aprobar/rechazar/solicitar informacion con motivos tipificados | G48: Terminado | H48: =IFERROR(INDEX(Config!$B$3:$B$8,MATCH($G48,Config!$A$3:$A$8,0)),0) | I48: =IFERROR(INDEX(Config!$C$3:$C$8,MATCH($G48,Config!$A$3:$A$8,0)),0) | J48: docs/fase-3/3.4 y 3.5. Activacion con seis requisitos
A49: 48 | B49: Ola 1 - MVP: operar sin Excel | C49: F5 | D49: Adquisicion de creadores | E49: 5.9 | F49: Aprobacion -> creacion de usuario + enlace seguro de contrasena + emails | G49: Terminado | H49: =IFERROR(INDEX(Config!$B$3:$B$8,MATCH($G49,Config!$A$3:$A$8,0)),0) | I49: =IFERROR(INDEX(Config!$C$3:$C$8,MATCH($G49,Config!$A$3:$A$8,0)),0) | J49: docs/fase-5/5.9-ENLACE-DE-CONTRASENA.md. Crea la cuenta, escribe creators.user_id y manda el enlace de 72 h. La cuenta nace con una contrasena que no conoce nadie
A50: 49 | B50: Ola 1 - MVP: operar sin Excel | C50: F5 | D50: Adquisicion de creadores | E50: 5.10 | F50: Blacklist | G50: En curso | H50: =IFERROR(INDEX(Config!$B$3:$B$8,MATCH($G50,Config!$A$3:$A$8,0)),0) | I50: =IFERROR(INDEX(Config!$C$3:$C$8,MATCH($G50,Config!$A$3:$A$8,0)),0) | J50: El estado blacklisted existe en creadores y clientes. Falta la pantalla y el motivo tipificado
A51: 50 | B51: Ola 1 - MVP: operar sin Excel | C51: F5 | D51: Adquisicion de creadores | E51: 5.11 | F51: QA de fase + Phase Review Report | G51: Pendiente | H51: =IFERROR(INDEX(Config!$B$3:$B$8,MATCH($G51,Config!$A$3:$A$8,0)),0) | I51: =IFERROR(INDEX(Config!$C$3:$C$8,MATCH($G51,Config!$A$3:$A$8,0)),0)
A52: 51 | B52: Ola 1 - MVP: operar sin Excel | C52: F6 | D52: Portal del creador | E52: 6.1 | F52: Shell del portal (PWA), navegacion movil, onboarding con barra de completitud | G52: Pendiente | H52: =IFERROR(INDEX(Config!$B$3:$B$8,MATCH($G52,Config!$A$3:$A$8,0)),0) | I52: =IFERROR(INDEX(Config!$C$3:$C$8,MATCH($G52,Config!$A$3:$A$8,0)),0)
A53: 52 | B53: Ola 1 - MVP: operar sin Excel | C53: F6 | D53: Portal del creador | E53: 6.2 | F53: Mi perfil: personal, ubicacion, idiomas, preferencias | G53: Pendiente | H53: =IFERROR(INDEX(Config!$B$3:$B$8,MATCH($G53,Config!$A$3:$A$8,0)),0) | I53: =IFERROR(INDEX(Config!$C$3:$C$8,MATCH($G53,Config!$A$3:$A$8,0)),0) | J53: El modelo y la pantalla de ADMIN existen; el portal del creador no
A54: 53 | B54: Ola 1 - MVP: operar sin Excel | C54: F6 | D54: Portal del creador | E54: 6.3 | F54: Mis redes: alta, edicion, actualizacion de estadisticas, evidencia | G54: Pendiente | H54: =IFERROR(INDEX(Config!$B$3:$B$8,MATCH($G54,Config!$A$3:$A$8,0)),0) | I54: =IFERROR(INDEX(Config!$C$3:$C$8,MATCH($G54,Config!$A$3:$A$8,0)),0) | J54: Idem: construido del lado admin en 3.7
A55: 54 | B55: Ola 1 - MVP: operar sin Excel | C55: F6 | D55: Portal del creador | E55: 6.4 | F55: Perfil profesional: nichos, formatos, restricciones, portfolio | G55: Pendiente | H55: =IFERROR(INDEX(Config!$B$3:$B$8,MATCH($G55,Config!$A$3:$A$8,0)),0) | I55: =IFERROR(INDEX(Config!$C$3:$C$8,MATCH($G55,Config!$A$3:$A$8,0)),0) | J55: Idem: construido del lado admin en 3.9
A56: 55 | B56: Ola 1 - MVP: operar sin Excel | C56: F6 | D56: Portal del creador | E56: 6.5 | F56: Mis tarifas por formato/moneda/vigencia | G56: Pendiente | H56: =IFERROR(INDEX(Config!$B$3:$B$8,MATCH($G56,Config!$A$3:$A$8,0)),0) | I56: =IFERROR(INDEX(Config!$C$3:$C$8,MATCH($G56,Config!$A$3:$A$8,0)),0) | J56: Idem: construido del lado admin en 3.9, con periodos sin solape
A57: 56 | B57: Ola 1 - MVP: operar sin Excel | C57: F6 | D57: Portal del creador | E57: 6.6 | F57: Datos fiscales y medios de pago (cifrado, enmascarado, verificacion de cambios) | G57: Pendiente | H57: =IFERROR(INDEX(Config!$B$3:$B$8,MATCH($G57,Config!$A$3:$A$8,0)),0) | I57: =IFERROR(INDEX(Config!$C$3:$C$8,MATCH($G57,Config!$A$3:$A$8,0)),0) | J57: Idem: construido del lado admin en 3.6 y 3.8. Bloqueo parcial por DEC-005
A58: 57 | B58: Ola 1 - MVP: operar sin Excel | C58: F6 | D58: Portal del creador | E58: 6.7 | F58: Flujo de aprobacion de cambios sensibles | G58: En curso | H58: =IFERROR(INDEX(Config!$B$3:$B$8,MATCH($G58,Config!$A$3:$A$8,0)),0) | I58: =IFERROR(INDEX(Config!$C$3:$C$8,MATCH($G58,Config!$A$3:$A$8,0)),0) | J58: La segregacion de dos personas ya esta en la base (ck_ctp_segregation, ck_cpm_segregation). Falta el flujo del lado del creador
A59: 58 | B59: Ola 1 - MVP: operar sin Excel | C59: F6 | D59: Portal del creador | E59: 6.8 | F59: Dashboard del creador (max. 6 KPIs) + notificaciones + barra de completitud con XP basico | G59: Pendiente | H59: =IFERROR(INDEX(Config!$B$3:$B$8,MATCH($G59,Config!$A$3:$A$8,0)),0) | I59: =IFERROR(INDEX(Config!$C$3:$C$8,MATCH($G59,Config!$A$3:$A$8,0)),0)
A60: 59 | B60: Ola 1 - MVP: operar sin Excel | C60: F6 | D60: Portal del creador | E60: 6.9 | F60: QA de fase + Phase Review Report | G60: Pendiente | H60: =IFERROR(INDEX(Config!$B$3:$B$8,MATCH($G60,Config!$A$3:$A$8,0)),0) | I60: =IFERROR(INDEX(Config!$C$3:$C$8,MATCH($G60,Config!$A$3:$A$8,0)),0)
A61: 60 | B61: Ola 1 - MVP: operar sin Excel | C61: F7 | D61: Motor de campana | E61: 7.0 | F61: Clientes y marcas: alta manual, contactos, datos fiscales por pais, entidad legal segun cobertura | G61: Terminado | H61: =IFERROR(INDEX(Config!$B$3:$B$8,MATCH($G61,Config!$A$3:$A$8,0)),0) | I61: =IFERROR(INDEX(Config!$C$3:$C$8,MATCH($G61,Config!$A$3:$A$8,0)),0) | J61: docs/fase-4/4.1 a 4.5. Bloqueo con motivo si ningun pais coincide (BR-LE-004)
A62: 61 | B62: Ola 1 - MVP: operar sin Excel | C62: F7 | D62: Motor de campana | E62: 7.1 | F62: Entidad Campaign + estados + transiciones + auditoria + billing_legal_entity_id congelado | G62: Terminado | H62: =IFERROR(INDEX(Config!$B$3:$B$8,MATCH($G62,Config!$A$3:$A$8,0)),0) | I62: =IFERROR(INDEX(Config!$C$3:$C$8,MATCH($G62,Config!$A$3:$A$8,0)),0) | J62: docs/fase-7/7.1. DEC-089 a DEC-091
A63: 62 | B63: Ola 1 - MVP: operar sin Excel | C63: F7 | D63: Motor de campana | E63: 7.2 | F63: Brief: requisitos y formatos, veto de BR-CAMPAIGN-004, ingreso declarado | G63: Terminado | H63: =IFERROR(INDEX(Config!$B$3:$B$8,MATCH($G63,Config!$A$3:$A$8,0)),0) | I63: =IFERROR(INDEX(Config!$C$3:$C$8,MATCH($G63,Config!$A$3:$A$8,0)),0) | J63: docs/fase-7/7.2. DEC-092 a DEC-094. Hashtags, menciones y assets quedaron fuera a proposito
A64: 63 | B64: Ola 1 - MVP: operar sin Excel | C64: F7 | D64: Motor de campana | E64: 7.3 | F64: Mercados de campana (multipais) - modelo completo, UI minima | G64: Terminado | H64: =IFERROR(INDEX(Config!$B$3:$B$8,MATCH($G64,Config!$A$3:$A$8,0)),0) | I64: =IFERROR(INDEX(Config!$C$3:$C$8,MATCH($G64,Config!$A$3:$A$8,0)),0) | J64: docs/fase-7/7.3. DEC-095 a DEC-098. Cierra T-33
A65: 64 | B65: Ola 1 - MVP: operar sin Excel | C65: F7 | D65: Motor de campana | E65: 7.4 | F65: Buscador de creadores con filtros reales + shortlist | G65: Terminado | H65: =IFERROR(INDEX(Config!$B$3:$B$8,MATCH($G65,Config!$A$3:$A$8,0)),0) | I65: =IFERROR(INDEX(Config!$C$3:$C$8,MATCH($G65,Config!$A$3:$A$8,0)),0) | J65: docs/fase-7/7.4. DEC-099 a DEC-102. Media BR-CAMPAIGN-007 implementada; abre T-34
A66: 65 | B66: Ola 1 - MVP: operar sin Excel | C66: F7 | D66: Motor de campana | E66: 7.5 | F66: Seleccion, cupos por formato, costo comprometido por creador (congelado) | G66: Terminado | H66: =IFERROR(INDEX(Config!$B$3:$B$8,MATCH($G66,Config!$A$3:$A$8,0)),0) | I66: =IFERROR(INDEX(Config!$C$3:$C$8,MATCH($G66,Config!$A$3:$A$8,0)),0) | J66: docs/fase-7/7.5. DEC-103 a DEC-105. BR-CAMPAIGN-005 nombraba un dato que no existia. Cupos por mercado siguen siendo objetivo, no tope
A67: 66 | B67: Ola 1 - MVP: operar sin Excel | C67: F7 | D67: Motor de campana | E67: 7.6 | F67: Invitaciones: envio, expiracion, aceptacion, rechazo con motivo, preguntas | G67: Terminado | H67: =IFERROR(INDEX(Config!$B$3:$B$8,MATCH($G67,Config!$A$3:$A$8,0)),0) | I67: =IFERROR(INDEX(Config!$C$3:$C$8,MATCH($G67,Config!$A$3:$A$8,0)),0) | J67: docs/fase-7/7.6-INVITACIONES.md. DEC-119 a DEC-123. Enlace de un solo uso, plazo por campana, rechazo con motivo y reinvitacion con constancia. Las PREGUNTAS quedan fuera: T-38
A68: 67 | B68: Ola 1 - MVP: operar sin Excel | C68: F7 | D68: Motor de campana | E68: 7.7 | F68: Panel de seguimiento de la campana (quien va en que estado) | G68: Terminado | H68: =IFERROR(INDEX(Config!$B$3:$B$8,MATCH($G68,Config!$A$3:$A$8,0)),0) | I68: =IFERROR(INDEX(Config!$C$3:$C$8,MATCH($G68,Config!$A$3:$A$8,0)),0) | J68: docs/fase-7/7.7-SEGUIMIENTO.md. DEC-127 y DEC-128. Embudo, cupo por mercado (cubierto = aceptado, no invitado), dinero con el margen detras de su permiso, y cuatro alertas
A69: 68 | B69: Ola 1 - MVP: operar sin Excel | C69: F7 | D69: Motor de campana | E69: 7.8 | F69: Logistica de producto: direccion de envio, lista de despacho, tracking, confirmacion de recepcion | G69: Pendiente | H69: =IFERROR(INDEX(Config!$B$3:$B$8,MATCH($G69,Config!$A$3:$A$8,0)),0) | I69: =IFERROR(INDEX(Config!$C$3:$C$8,MATCH($G69,Config!$A$3:$A$8,0)),0)
A70: 69 | B70: Ola 1 - MVP: operar sin Excel | C70: F7 | D70: Motor de campana | E70: 7.9 | F70: Campanas UGC vs distribucion | G70: Pendiente | H70: =IFERROR(INDEX(Config!$B$3:$B$8,MATCH($G70,Config!$A$3:$A$8,0)),0) | I70: =IFERROR(INDEX(Config!$C$3:$C$8,MATCH($G70,Config!$A$3:$A$8,0)),0) | J70: El objetivo ugc ya es un valor valido de la campana
A71: 70 | B71: Ola 1 - MVP: operar sin Excel | C71: F7 | D71: Motor de campana | E71: 7.10 | F71: Gestion de reemplazos: dropped/replaced, motivo, lista de espera, reasignacion de presupuesto | G71: Pendiente | H71: =IFERROR(INDEX(Config!$B$3:$B$8,MATCH($G71,Config!$A$3:$A$8,0)),0) | I71: =IFERROR(INDEX(Config!$C$3:$C$8,MATCH($G71,Config!$A$3:$A$8,0)),0)
A72: 71 | B72: Ola 1 - MVP: operar sin Excel | C72: F7 | D72: Motor de campana | E72: 7.11 | F72: Deteccion de conflictos de marca y exclusividades vigentes | G72: En curso | H72: =IFERROR(INDEX(Config!$B$3:$B$8,MATCH($G72,Config!$A$3:$A$8,0)),0) | I72: =IFERROR(INDEX(Config!$C$3:$C$8,MATCH($G72,Config!$A$3:$A$8,0)),0) | J72: MEDIA hecha en 7.4: la categoria que el creador declaro que no trabaja ya excluye (DEC-100). Faltan competidores y exclusividades vigentes
A73: 72 | B73: Ola 1 - MVP: operar sin Excel | C73: F7 | D73: Motor de campana | E73: 7.12 | F73: Calendario de campana | G73: Pendiente | H73: =IFERROR(INDEX(Config!$B$3:$B$8,MATCH($G73,Config!$A$3:$A$8,0)),0) | I73: =IFERROR(INDEX(Config!$C$3:$C$8,MATCH($G73,Config!$A$3:$A$8,0)),0)
A74: 73 | B74: Ola 1 - MVP: operar sin Excel | C74: F7 | D74: Motor de campana | E74: 7.13 | F74: QA de fase + Phase Review Report | G74: Pendiente | H74: =IFERROR(INDEX(Config!$B$3:$B$8,MATCH($G74,Config!$A$3:$A$8,0)),0) | I74: =IFERROR(INDEX(Config!$C$3:$C$8,MATCH($G74,Config!$A$3:$A$8,0)),0)
A75: 74 | B75: Ola 1 - MVP: operar sin Excel | C75: F8 | D75: Contenido, revision y evidencia | E75: 8.1 | F75: Entregables: tipos, subida desde movil, enlaces, captions, hashtags | G75: Terminado | H75: =IFERROR(INDEX(Config!$B$3:$B$8,MATCH($G75,Config!$A$3:$A$8,0)),0) | I75: =IFERROR(INDEX(Config!$C$3:$C$8,MATCH($G75,Config!$A$3:$A$8,0)),0) | J75: docs/fase-8/8.1-ENTREGABLES.md. DEC-129 a DEC-132. Se generan solos al aceptar, del brief EFECTIVO del mercado (N-03). Enlace https obligatorio + imagen opcional. Si faltan los hashtags del brief no se envia y se dice cuales. Portal del creador (/mis-entregas) con creator.portal, primer permiso de ambito EXTERNAL. 32 pruebas.
A76: 75 | B76: Ola 1 - MVP: operar sin Excel | C76: F8 | D76: Contenido, revision y evidencia | E76: 8.2 | F76: Versionado append-only + puntero de version actual | G76: Terminado | H76: =IFERROR(INDEX(Config!$B$3:$B$8,MATCH($G76,Config!$A$3:$A$8,0)),0) | I76: =IFERROR(INDEX(Config!$C$3:$C$8,MATCH($G76,Config!$A$3:$A$8,0)),0) | J76: docs/fase-8/8.2-VERSION-VIGENTE.md. DEC-137 y DEC-138. El append-only es de 8.1 (uq_dv_number con la fila bloqueada); 8.2 anade el puntero a la version APROBADA con clave ajena COMPUESTA --garantiza que la version es de ESE entregable-- y la reapertura con motivo de lista cerrada y firma, que no deshace nada. Ademas tg_dv_entregable_abierto: el veto de «no se entrega sobre algo cerrado» vivia en el servicio desde 8.1 y la base no lo conocia (T-47).
A77: 76 | B77: Ola 1 - MVP: operar sin Excel | C77: F8 | D77: Contenido, revision y evidencia | E77: 8.3 | F77: Cola de revision interna + comentarios por version + solicitud de correccion | G77: Terminado | H77: =IFERROR(INDEX(Config!$B$3:$B$8,MATCH($G77,Config!$A$3:$A$8,0)),0) | I77: =IFERROR(INDEX(Config!$C$3:$C$8,MATCH($G77,Config!$A$3:$A$8,0)),0) | J77: docs/fase-8/8.3-REVISION.md. DEC-133 a DEC-136. Bandeja GLOBAL ordenada por lo que lleva mas esperando. Solo las rondas del CLIENTE cuentan y son POR ENTREGABLE (el contador estaba en campaign_creators). Pasarse bloquea y exige decidir si se cobra o se absorbe, firmado. Tres permisos: content.review, content.approve y content.extra_round. tg_cvw_inmutable cierra el append-only que 2.12 afirmaba sin impedir nada. 30 pruebas.
A78: 77 | B78: Ola 1 - MVP: operar sin Excel | C78: F8 | D78: Contenido, revision y evidencia | E78: 8.4 | F78: Aprobacion interna y limite de rondas | G78: Terminado | H78: =IFERROR(INDEX(Config!$B$3:$B$8,MATCH($G78,Config!$A$3:$A$8,0)),0) | I78: =IFERROR(INDEX(Config!$C$3:$C$8,MATCH($G78,Config!$A$3:$A$8,0)),0) | J78: docs/fase-8/8.4-TECHO-DE-RONDAS.md. El techo lo impone la BASE, no un if: solo la correccion del CLIENTE gasta ronda y una ronda de mas se declara.
A79: 78 | B79: Ola 1 - MVP: operar sin Excel | C79: F8 | D79: Contenido, revision y evidencia | E79: 8.5 | F79: Aprobacion del cliente por enlace firmado (sin portal completo) | G79: Terminado | H79: =IFERROR(INDEX(Config!$B$3:$B$8,MATCH($G79,Config!$A$3:$A$8,0)),0) | I79: =IFERROR(INDEX(Config!$C$3:$C$8,MATCH($G79,Config!$A$3:$A$8,0)),0) | J79: docs/fase-8/8.5-APROBACION-DEL-CLIENTE.md. Enlace de un solo uso, sin portal ni contrasena, y sin un solo importe. Queda su hora y su IP.
A80: 79 | B80: Ola 1 - MVP: operar sin Excel | C80: F8 | D80: Contenido, revision y evidencia | E80: 8.6 | F80: Programacion y registro de publicacion (URL) | G80: Terminado | H80: =IFERROR(INDEX(Config!$B$3:$B$8,MATCH($G80,Config!$A$3:$A$8,0)),0) | I80: =IFERROR(INDEX(Config!$C$3:$C$8,MATCH($G80,Config!$A$3:$A$8,0)),0) | J80: docs/fase-8/8.6-PUBLICACION.md. DEC-139 a DEC-141. El creador pega el enlace desde su portal y el equipo puede hacerlo por el; solo se publica lo APROBADO y esa version (snapshot con clave ajena compuesta). La red se deduce del enlace con platforms.url_pattern y tiene que ser la del brief. La huella normaliza la URL para que uq_pub_fingerprint sirva de algo. 31 pruebas. La PROGRAMACION queda fuera: hoy se registra lo ya publicado.
A81: 80 | B81: Ola 1 - MVP: operar sin Excel | C81: F8 | D81: Contenido, revision y evidencia | E81: 8.7 | F81: Verificacion de publicacion + archivado de evidencia | G81: Terminado | H81: =IFERROR(INDEX(Config!$B$3:$B$8,MATCH($G81,Config!$A$3:$A$8,0)),0) | I81: =IFERROR(INDEX(Config!$C$3:$C$8,MATCH($G81,Config!$A$3:$A$8,0)),0) | J81: docs/fase-8/8.7-EVIDENCIA.md. DEC-142 a DEC-144. La evidencia es una CAPTURA y no una comprobacion HTTP: Instagram y TikTok responden igual a un post vivo que a un bloqueo, y de verified cuelga el pago. Permiso propio content.verify. Si el post no esta, el entregable vuelve al CREADOR y se le avisa. permanence_until se calcula al verificar. T-50: una rechazada bloqueaba su propio enlace (columna puerta viva_gate, la decimoquinta). 21 pruebas.
A82: 81 | B82: Ola 1 - MVP: operar sin Excel | C82: F8 | D82: Contenido, revision y evidencia | E82: 8.8 | F82: Control de permanencia minima del post | G82: Terminado | H82: =IFERROR(INDEX(Config!$B$3:$B$8,MATCH($G82,Config!$A$3:$A$8,0)),0) | I82: =IFERROR(INDEX(Config!$C$3:$C$8,MATCH($G82,Config!$A$3:$A$8,0)),0) | J82: docs/fase-8/8.8-PERMANENCIA.md. Bandeja, historico que no se edita y comando diario a las 06:00. Si el post desaparece, el pago se para y el creador se entera.
A83: 82 | B83: Ola 1 - MVP: operar sin Excel | C83: F8 | D83: Contenido, revision y evidencia | E83: 8.9 | F83: Hilos de mensajes creador <-> equipo por campana | G83: Pendiente | H83: =IFERROR(INDEX(Config!$B$3:$B$8,MATCH($G83,Config!$A$3:$A$8,0)),0) | I83: =IFERROR(INDEX(Config!$C$3:$C$8,MATCH($G83,Config!$A$3:$A$8,0)),0) | J83: Sin empezar. Hoy la conversacion con el creador es el correo de 7.6b.
A84: 83 | B84: Ola 1 - MVP: operar sin Excel | C84: F8 | D84: Contenido, revision y evidencia | E84: 8.10 | F84: Derechos de uso: alcance, territorio, canales, exclusividad, vigencia | G84: Pendiente | H84: =IFERROR(INDEX(Config!$B$3:$B$8,MATCH($G84,Config!$A$3:$A$8,0)),0) | I84: =IFERROR(INDEX(Config!$C$3:$C$8,MATCH($G84,Config!$A$3:$A$8,0)),0) | J84: DESBLOQUEADA (2026-08-30). Los terminos ya existen y se editan desde el admin (9.16); los derechos de uso son la seccion 6 del texto base, marcada [REVISAR]. Lo que falta es MODELARLOS: licencia, territorio, plazo y exclusividad no son hoy datos de la campana, y el propio texto lo advierte.
A85: 84 | B85: Ola 1 - MVP: operar sin Excel | C85: F8 | D85: Contenido, revision y evidencia | E85: 8.11 | F85: QA de fase + Phase Review Report | G85: Terminado | H85: =IFERROR(INDEX(Config!$B$3:$B$8,MATCH($G85,Config!$A$3:$A$8,0)),0) | I85: =IFERROR(INDEX(Config!$C$3:$C$8,MATCH($G85,Config!$A$3:$A$8,0)),0) | J85: docs/fase-8/8.11-QA-DE-FASE.md. Septima puerta. Encontro nueve suites que se habrian puesto verdes con el motor apagado (T-55) y dos cosas mas que la fase daba por hechas.
A86: 85 | B86: Ola 1 - MVP: operar sin Excel | C86: F8 | D86: Contenido, revision y evidencia | E86: 8.12 | F86: La sociedad que factura, explicada en la ficha de campana | G86: Terminado | H86: =IFERROR(INDEX(Config!$B$3:$B$8,MATCH($G86,Config!$A$3:$A$8,0)),0) | I86: =IFERROR(INDEX(Config!$C$3:$C$8,MATCH($G86,Config!$A$3:$A$8,0)),0) | J86: FUERA DEL ALCANCE ORIGINAL. docs/fase-8/8.12-LA-SOCIEDAD-QUE-FACTURA.md. Salio T-58: la pantalla llevaba desde 7.1 imprimiendo la sociedad de HOY bajo el rotulo de la guardada.
... A104: 103 | B104: Ola 1 - MVP: operar sin Excel | C104: F9 | D104: Finanzas | E104: 9.17 | F104: La marca es un dato: nombre, lema, pie legal, logotipo, favicon, tres colores y tipografia configurables desde el admin | G104: Terminado | H104: =IFERROR(INDEX(Config!$B$3:$B$8,MATCH($G104,Config!$A$3:$A$8,0)),0) | I104: =IFERROR(INDEX(Config!$C$3:$C$8,MATCH($G104,Config!$A$3:$A$8,0)),0) | J104: 2026-08-31. «LATAM Social» estaba escrito en tres plantillas y el favicon era un archivo del repositorio; platform_brands guardaba todo eso desde 2.10 y nadie la leia. Pantalla /marca con permiso propio brand.manage. Una sola marca por defecto (28.a columna puerta). Lo que falta no bloquea: badge rojo/ambar/verde (DEC-200). El logotipo se sirve por una puerta publica sin identificador porque la pantalla de acceso la ve quien no ha entrado (DEC-201). DEC-199 a DEC-204. 21 pruebas, 19 aserciones SQL en los dos motores. Salio T-72 --las clases de color no existian desde la Fase 4-- y un 403 que salia como 500. docs/fase-9/9.17-LA-MARCA-ES-UN-DATO.md
A105: 103b | B105: Ola 1 - MVP: operar sin Excel | C105: F9 | D105: Finanzas | E105: 9.17b | F105: Que falta por configurar, en una sola pantalla: cinco areas con badges de prioridad | G105: Terminado | H105: =IFERROR(INDEX(Config!$B$3:$B$8,MATCH($G105,Config!$A$3:$A$8,0)),0) | I105: =IFERROR(INDEX(Config!$C$3:$C$8,MATCH($G105,Config!$A$3:$A$8,0)),0) | J105: 2026-08-31. 9.16 y 9.17 dejaron cada una su lista de avisos y cada una solo se veia entrando en su pantalla; el correo escribiendose en un archivo en vez de enviarse no lo decia ninguna. Preparacion (Shared) las junta y cada modulo declara su area desde su ServiceProvider. Si no puedes arreglarlo, no lo ves (DEC-206). Una comprobacion que revienta no tumba el panel (DEC-207). DEC-205 a DEC-208. 12 pruebas, sin migracion. docs/fase-9/9.17b-PANEL-DE-CONFIGURACION.md
A106: 103c | B106: Ola 1 - MVP: operar sin Excel | C106: F9 | D106: Finanzas | E106: 9.17c | F106: El domicilio fiscal, con la forma (ubigeo, DANE) que exige cada pais | G106: Terminado | H106: =IFERROR(INDEX(Config!$B$3:$B$8,MATCH($G106,Config!$A$3:$A$8,0)),0) | I106: =IFERROR(INDEX(Config!$C$3:$C$8,MATCH($G106,Config!$A$3:$A$8,0)),0) | J106: 2026-08-31. El comprobante peruano lleva el ubigeo y legal_entities no tenia ni el distrito ni el codigo. No se llama ubigeo: la forma la declara el PAIS y la imponen dos disparadores cruzados, asi que el formulario pide «Ubigeo» a una peruana y «Codigo DANE» a una colombiana sin una linea de codigo por pais (DEC-209). El establecimiento nace en 0000 (DEC-210); que falte no bloquea, sale en rojo en el panel (DEC-211). Salio un 1267 de colacion que habria reventado cada alta con codigo, invisible mientras el campo viniera nulo. 10 pruebas, 19 aserciones SQL en los dos motores. docs/fase-9/9.17c-DOMICILIO-FISCAL.md
A107: 103d | B107: Ola 1 - MVP: operar sin Excel | C107: F9 | D107: Finanzas | E107: 9.17d | F107: Las credenciales de cada API en un solo sitio | G107: Terminado | H107: =IFERROR(INDEX(Config!$B$3:$B$8,MATCH($G107,Config!$A$3:$A$8,0)),0) | I107: =IFERROR(INDEX(Config!$C$3:$C$8,MATCH($G107,Config!$A$3:$A$8,0)),0) | J107: 2026-08-31. Prerrequisito de 9.9. Tres tablas propias --proveedores, conexiones, credenciales-- porque una sociedad es QUIEN factura y una conexion es CON QUE se conecta uno (DEC-223). Las asignaciones de docs/12 NO se construyen: resuelven un problema que hoy no existe, y esta escrito donde (DEC-224). Rotar versiona, no pisa (DEC-225); la bitacora anota QUE cambio, nunca el valor (DEC-226); una conexion activa exige https (DEC-227). 953 pruebas; 2096 aserciones SQL en MariaDB y 2086 en MySQL 8. Destapo T-75. docs/fase-9/9.17d-CREDENCIALES-DE-API.md
A108: 104 | B108: Ola 1 - MVP: operar sin Excel | C108: F9 | D108: Finanzas | E108: 9.18 | F108: Se pacta lo que el creador recibe: retencion sobre el neto y umbral de rentabilidad | G108: Terminado | H108: =IFERROR(INDEX(Config!$B$3:$B$8,MATCH($G108,Config!$A$3:$A$8,0)),0) | I108: =IFERROR(INDEX(Config!$C$3:$C$8,MATCH($G108,Config!$A$3:$A$8,0)),0) | J108: 2026-08-31. Se teclea 100 y la campana provisiona 141,8440; el mensaje dice que para dejar el 20 % el ingreso tendria que llegar a 170,21. Las tres cifras del ejemplo de Q-40. La politica (retencion, umbral y sobre que se calcula) vive en pricing_policies con vigencia e historia. La pregunta «markup o margen» NO habia que hacerla: es una columna configurable con las dos cifras a la vista (DEC-213). DEC-212 a DEC-215. 14 pruebas, 25 aserciones SQL en los dos motores. docs/fase-9/9.18-POLITICA-Y-NETO-PACTADO.md
A109: 105 | B109: Ola 1 - MVP: operar sin Excel | C109: F9 | D109: Finanzas | E109: 9.19 | F109: Los terminos nuevos hay que volver a aceptarlos: plazo, solo lectura y muro | G109: Terminado | H109: =IFERROR(INDEX(Config!$B$3:$B$8,MATCH($G109,Config!$A$3:$A$8,0)),0) | I109: =IFERROR(INDEX(Config!$C$3:$C$8,MATCH($G109,Config!$A$3:$A$8,0)),0) | J109: 2026-08-31. Los tres escalones de Q-46: dentro del plazo se pasa con una franja; pasado el plazo se mira y no se toca (filtrado por metodo HTTP, cubre toda pantalla que exista o se anada); pasada la ventana, solo la pantalla de aceptar. Los plazos van en la VERSION y son inmutables (DEC-216). El reloj empieza cuando le toca a cada uno (DEC-217). La pantalla del muro no lleva permiso: es la unica salida (DEC-218). Y arregla T-73, reportado en produccion. DEC-216 a DEC-219. 16 pruebas, 11 aserciones SQL. docs/fase-9/9.19-REACEPTACION-DE-TERMINOS.md
A110: 105b | B110: Ola 1 - MVP: operar sin Excel | C110: F9 | D110: Finanzas | E110: 9.19b | F110: El aviso por correo de la reaceptacion, y la frontera Core/Creator | G110: Terminado | H110: =IFERROR(INDEX(Config!$B$3:$B$8,MATCH($G110,Config!$A$3:$A$8,0)),0) | I110: =IFERROR(INDEX(Config!$C$3:$C$8,MATCH($G110,Config!$A$3:$A$8,0)),0) | J110: 2026-08-31. Al publicar una version DE FONDO sale un correo a cada creador activo, y el texto dice que pasa despues. Core levanta un evento y Creator escucha, asi que un SMTP caido no tumba la publicacion (DEC-220). Cada envio en su propio try (DEC-222). Y corrige T-74, que era mio: Terminos leia creators desde Core, la frontera rota que deptrac no ve. Hay una prueba que lee el codigo fuente porque no hay herramienta que lo cace. DEC-220 a DEC-222. 20 pruebas. Sin migracion. docs/fase-9/9.19b-EL-AVISO-POR-CORREO.md
A111: 106 | B111: Ola 1 - MVP: operar sin Excel | C111: F9 | D111: Finanzas | E111: 9.14b | F111: Auditoria de seguridad: el muro de rutas | G111: Terminado | H111: =IFERROR(INDEX(Config!$B$3:$B$8,MATCH($G111,Config!$A$3:$A$8,0)),0) | I111: =IFERROR(INDEX(Config!$C$3:$C$8,MATCH($G111,Config!$A$3:$A$8,0)),0) | J111: FUERA DEL ALCANCE ORIGINAL como iteracion propia. 145 rutas x 3 roles de fuera, 371 aserciones. Cerro dos rutas del framework sobre el disco privado. Salio T-67.
A112: 107 | B112: Ola 1 - MVP: operar sin Excel | C112: F9 | D112: Finanzas | E112: 9.15 | F112: Que los archivos se puedan ver: una puerta con permiso por archivo | G112: Terminado | H112: =IFERROR(INDEX(Config!$B$3:$B$8,MATCH($G112,Config!$A$3:$A$8,0)),0) | I112: =IFERROR(INDEX(Config!$C$3:$C$8,MATCH($G112,Config!$A$3:$A$8,0)),0) | J112: FUERA DEL ALCANCE ORIGINAL. docs/fase-9/9.15-VER-UN-ARCHIVO.md. Cierra T-67. Se guardaban desde la Fase 3 y no los servia nadie. Cada modulo declara quien puede ver SUS archivos (DEC-197) y el permiso se mira en cada peticion (DEC-198). Desbloquea 9.17: un logotipo guardado hay que poder servirlo.
A113: 109 | B113: Ola 1 - MVP: operar sin Excel | C113: F10 | D113: Medicion y reportes | E113: 10.1 | F113: Snapshots de metricas por publicacion con fuente y timestamp | G113: Pendiente | H113: =IFERROR(INDEX(Config!$B$3:$B$8,MATCH($G113,Config!$A$3:$A$8,0)),0) | I113: =IFERROR(INDEX(Config!$C$3:$C$8,MATCH($G113,Config!$A$3:$A$8,0)),0) | J113: El patron ya existe para redes sociales (social_account_snapshots)
A114: 110 | B114: Ola 1 - MVP: operar sin Excel | C114: F10 | D114: Medicion y reportes | E114: 10.2 | F114: Captura asistida (creador declara + sube captura; operador valida) | G114: Pendiente | H114: =IFERROR(INDEX(Config!$B$3:$B$8,MATCH($G114,Config!$A$3:$A$8,0)),0) | I114: =IFERROR(INDEX(Config!$C$3:$C$8,MATCH($G114,Config!$A$3:$A$8,0)),0)
A115: 111 | B115: Ola 1 - MVP: operar sin Excel | C115: F10 | D115: Medicion y reportes | E115: 10.3 | F115: Consolidacion por creador / plataforma / campana | G115: Pendiente | H115: =IFERROR(INDEX(Config!$B$3:$B$8,MATCH($G115,Config!$A$3:$A$8,0)),0) | I115: =IFERROR(INDEX(Config!$C$3:$C$8,MATCH($G115,Config!$A$3:$A$8,0)),0)
A116: 112 | B116: Ola 1 - MVP: operar sin Excel | C116: F10 | D116: Medicion y reportes | E116: 10.4 | F116: Reporte de campana reproducible (fecha de corte fija) | G116: Pendiente | H116: =IFERROR(INDEX(Config!$B$3:$B$8,MATCH($G116,Config!$A$3:$A$8,0)),0) | I116: =IFERROR(INDEX(Config!$C$3:$C$8,MATCH($G116,Config!$A$3:$A$8,0)),0)
A117: 113 | B117: Ola 1 - MVP: operar sin Excel | C117: F10 | D117: Medicion y reportes | E117: 10.5 | F117: Entrega del reporte al cliente por enlace firmado + exportacion PDF | G117: Pendiente | H117: =IFERROR(INDEX(Config!$B$3:$B$8,MATCH($G117,Config!$A$3:$A$8,0)),0) | I117: =IFERROR(INDEX(Config!$C$3:$C$8,MATCH($G117,Config!$A$3:$A$8,0)),0)
A118: 114 | B118: Ola 1 - MVP: operar sin Excel | C118: F10 | D118: Medicion y reportes | E118: 10.6 | F118: Dashboards por rol (Superadmin, Ops, Campaign Mgr, Finance, Creator) | G118: Pendiente | H118: =IFERROR(INDEX(Config!$B$3:$B$8,MATCH($G118,Config!$A$3:$A$8,0)),0) | I118: =IFERROR(INDEX(Config!$C$3:$C$8,MATCH($G118,Config!$A$3:$A$8,0)),0)
A119: 115 | B119: Ola 1 - MVP: operar sin Excel | C119: F10 | D119: Medicion y reportes | E119: 10.7 | F119: Exportaciones CSV/XLSX como job en cola | G119: Pendiente | H119: =IFERROR(INDEX(Config!$B$3:$B$8,MATCH($G119,Config!$A$3:$A$8,0)),0) | I119: =IFERROR(INDEX(Config!$C$3:$C$8,MATCH($G119,Config!$A$3:$A$8,0)),0) | J119: Depende de 4.8
A120: 116 | B120: Ola 1 - MVP: operar sin Excel | C120: F10 | D120: Medicion y reportes | E120: 10.8 | F120: Indicador de carga y capacidad del equipo | G120: Pendiente | H120: =IFERROR(INDEX(Config!$B$3:$B$8,MATCH($G120,Config!$A$3:$A$8,0)),0) | I120: =IFERROR(INDEX(Config!$C$3:$C$8,MATCH($G120,Config!$A$3:$A$8,0)),0)
A121: 117 | B121: Ola 1 - MVP: operar sin Excel | C121: F10 | D121: Medicion y reportes | E121: 10.9 | F121: QA de fase + Phase Review Report. HITO: fin del MVP | G121: Pendiente | H121: =IFERROR(INDEX(Config!$B$3:$B$8,MATCH($G121,Config!$A$3:$A$8,0)),0) | I121: =IFERROR(INDEX(Config!$C$3:$C$8,MATCH($G121,Config!$A$3:$A$8,0)),0)
A122: 118 | B122: Ola 2 - Escalar comercialmente | C122: F11 | D122: Adquisicion de marcas y CRM | E122: 11.1 | F122: Landing B2B | G122: Pendiente | H122: =IFERROR(INDEX(Config!$B$3:$B$8,MATCH($G122,Config!$A$3:$A$8,0)),0) | I122: =IFERROR(INDEX(Config!$C$3:$C$8,MATCH($G122,Config!$A$3:$A$8,0)),0)
A123: 119 | B123: Ola 2 - Escalar comercialmente | C123: F11 | D123: Adquisicion de marcas y CRM | E123: 11.2 | F123: Formulario de lead + UTM + consentimiento | G123: Pendiente | H123: =IFERROR(INDEX(Config!$B$3:$B$8,MATCH($G123,Config!$A$3:$A$8,0)),0) | I123: =IFERROR(INDEX(Config!$C$3:$C$8,MATCH($G123,Config!$A$3:$A$8,0)),0)
A124: 120 | B124: Ola 2 - Escalar comercialmente | C124: F11 | D124: Adquisicion de marcas y CRM | E124: 11.3 | F124: Lead, asignacion y SLA | G124: Pendiente | H124: =IFERROR(INDEX(Config!$B$3:$B$8,MATCH($G124,Config!$A$3:$A$8,0)),0) | I124: =IFERROR(INDEX(Config!$C$3:$C$8,MATCH($G124,Config!$A$3:$A$8,0)),0)
A125: 121 | B125: Ola 2 - Escalar comercialmente | C125: F11 | D125: Adquisicion de marcas y CRM | E125: 11.4 | F125: Pipeline Kanban configurable | G125: Pendiente | H125: =IFERROR(INDEX(Config!$B$3:$B$8,MATCH($G125,Config!$A$3:$A$8,0)),0) | I125: =IFERROR(INDEX(Config!$C$3:$C$8,MATCH($G125,Config!$A$3:$A$8,0)),0)
A126: 122 | B126: Ola 2 - Escalar comercialmente | C126: F11 | D126: Adquisicion de marcas y CRM | E126: 11.5 | F126: Actividades, notas, tareas y recordatorios | G126: Pendiente | H126: =IFERROR(INDEX(Config!$B$3:$B$8,MATCH($G126,Config!$A$3:$A$8,0)),0) | I126: =IFERROR(INDEX(Config!$C$3:$C$8,MATCH($G126,Config!$A$3:$A$8,0)),0)
A127: 123 | B127: Ola 2 - Escalar comercialmente | C127: F11 | D127: Adquisicion de marcas y CRM | E127: 11.6 | F127: Conversion Lead -> Cliente con trazabilidad | G127: Pendiente | H127: =IFERROR(INDEX(Config!$B$3:$B$8,MATCH($G127,Config!$A$3:$A$8,0)),0) | I127: =IFERROR(INDEX(Config!$C$3:$C$8,MATCH($G127,Config!$A$3:$A$8,0)),0)
A128: 124 | B128: Ola 2 - Escalar comercialmente | C128: F11 | D128: Adquisicion de marcas y CRM | E128: 11.7 | F128: Organizaciones cliente, marcas y contactos | G128: Terminado | H128: =IFERROR(INDEX(Config!$B$3:$B$8,MATCH($G128,Config!$A$3:$A$8,0)),0) | I128: =IFERROR(INDEX(Config!$C$3:$C$8,MATCH($G128,Config!$A$3:$A$8,0)),0) | J128: Ya construido en 7.0 / docs/fase-4
...

Sheet Tareas
A1: Tareas técnicas y de gestión (T-XX). Nacen cuando algo se descubre roto o a medias y no se puede arreglar en el momento. Fuente: docs/05-DECISION-LOG.md. Las abiertas van arriba.
A2: ID | B2: Estado | C2: Prioridad | D2: Que hay que hacer | E2: Cuando hace falta | F2: Quien la desbloquea | G2: Detalle
A3: T-09 | B3: Abierta | C3: Critica | D3: Que un abogado revise el texto base de los terminos. | E3: Antes de la primera discusion real con un creador | F3: Tu abogado | G3: Ya NO bloquea nada (9.16): el sistema arranca con un texto de partida sembrado y publicado, se edita desde el admin, y los creadores se pueden activar hoy. Lo que queda es la revision juridica de ese texto, que la propia pantalla marca en rojo mientras no ocurra --review_status = sin_revisar-- y que ademas cuenta las once marcas [REVISAR] que el borrador lleva dentro. Los tres bloques que mas necesitan al abogado: menores de edad (hoy la aceptacion se registra a nombre del creador y no del tutor), propiedad intelectual del contenido --el sistema no modela licencia, exclusividad ni plazo de uso, y son el nucleo de un contrato de marketing de creadores-- y ley aplicable y fuero. Insumos en docs/legal/Insumos-terminos-creador.docx
A4: T-69 | B4: Abierta | C4: Critica | D4: Repasar toda decision anterior que fije un valor en el codigo, bajo DEC-190. | E4: Trabajo de fondo | F4: Equipo de desarrollo | G4: El principio de white label llego en 9.16 y hay noventa decisiones tomadas antes. Las que se sabe que hay que revisar: los 30 dias de plazo de pago (BR-FIN-012, hoy por creador pero con el 30 de fabrica en el codigo), el periodo de enfriamiento de un medio de pago (BR-FIN-006), las dos rondas incluidas (BR-CONTENT-003), el corte de 10 dias de una tasa rancia (DEC-160), los umbrales del buscador de creadores, y la marca de la plataforma. Ninguno esta mal hoy; lo que esta mal es que para cambiarlos haya que tocar codigo. Se hace por partes y con su iteracion, no de golpe
A5: T-29 | B5: Abierta | D5: Cinco iteraciones de la Fase 3 sin documento. | E5: Antes de que se olvide el porque | F5: Equipo de desarrollo | G5: 3.9 (tarifas), 3.11 (anulacion), 3.12 (no borrar), 3.13 (terminos) y 3.14 (rotacion de clave). Todas las demas iteraciones del proyecto tienen el suyo. El trabajo esta hecho y verificado por sus suites; lo que falta es el documento que explica por que, que es justo lo que no se puede reconstruir leyendo el codigo dentro de seis meses
A6: T-34 | B6: Abierta | D6: BR-CREATOR-012 dice menos de lo que el esquema implica. | E6: Al revisar docs/06 | F6: Equipo de desarrollo | G6: El texto habla solo de creadores CON TUTELA ACTIVA, y min_creator_age es una columna de campaigns que no menciona la tutela: aplicarla solo a los menores dejaria pasar a un creador de 20 anos en una campana de 21. En 7.4 se aplica a TODOS, y la edad minima efectiva es el maximo entre la de la campana y la de las categorias de la marca. Lo que hay que corregir es el texto de la regla, no el codigo
A7: T-35 | B7: Abierta | D7: El runbook de despliegue existe pero nadie lo ha ejecutado. | E7: Al primer despliegue | F7: Tu (primer despliegue) | G7: docs/18-RUNBOOK-DESPLIEGUE.md (2026-08-26) recoge por fin los pasos que vivian en conversaciones: los dos GRANT de DEC-085, las DOS lineas de cron --la de la cola y la del scheduler, que no son la misma y falta cualquiera de las dos rompe algo distinto--, el orden de despliegue y las comprobaciones posteriores. Escribirlo no lo ejecuta: sigue pendiente hacerlo en el servidor real y corregir el documento con lo que se descubra, porque un runbook que nadie ha seguido es una hipotesis
A8: T-37 | B8: Abierta | D8: VARBINARY faltaba en el reconocedor de tipos de generar-triggers.py y puede faltar algo mas. | E8: Antes de anadir un tipo de columna nuevo | F8: Equipo de desarrollo | G8: ^BINARY no casaba con VARBINARY(16): la columna no entraba en la lista y el CHECK que la nombraba se generaba como un disparador con el identificador suelto. Arreglado, y se vio porque MySQL grita; el hueco llevaba desde la Fase 2 en audit_logs.ip_address y creator_identity_verifications.ip_address, dos columnas que nunca habian aparecido en un CHECK. Lo que queda por hacer es la comprobacion que lo habria cazado antes: que el generador falle cuando una linea de una tabla parece definicion de columna y el reconocedor de tipos la descarta, en vez de seguir en silencio
A9: T-64 | B9: Abierta | D9: La matriz de permisos del seeder concede y no revoca nunca. | E9: Antes de la siguiente revocacion | F9: Equipo de desarrollo | G9: CimientosSeeder aplica los roles con updateOrInsert, asi que quitar una linea de la matriz no quita el permiso en ninguna base que ya lo tenga --produccion incluida-- y el permiso sigue puesto sin que nada lo diga. Se descubrio al revocar campaign.view_margin en 9.10a, y alli se resolvio con un DELETE explicito en la migracion; el problema es general y el siguiente «quitale ese permiso a ese rol» fallara igual. Hace falta decidir la forma: o la matriz se vuelve autoritativa --y entonces borra lo que no aparece, con el riesgo de tumbar concesiones hechas a mano-- o cada revocacion pasa por su migracion y eso se escribe donde se pueda encontrar
A10: T-65 | B10: Abierta | D10: 147 reglas del esquema siguen sin que nadie les pregunte nada. | E10: Trabajo de fondo | F10: Equipo de desarrollo | G10: Bajo de 167 a 147 al cubrir las veinte del camino del dinero (9.14). La mayor concentracion que queda esta en invoices (12), creator_tax_profiles (9) y creator_payment_methods (7): tablas de dinero y de datos sensibles de las Fases 2 y 3. Bajarlo es trabajo mecanico y medible, y el trinquete de MUDAS-BASE impide que suba mientras tanto. Cuidado con la forma facil de bajarlo mal: una asercion que admite OTRO motivo por la alternancia de porque() cuenta como cubierta y no ha preguntado nada --paso en esta misma iteracion con las dos reglas de payments--
A11: T-66 | B11: Abierta | D11: Los mensajes de las restricciones de la Fase 2 son genericos. | E11: Antes de que un usuario real vea un 45000 | F11: Equipo de desarrollo | G11: Dicen «Restriccion ck_ledger_sign incumplida», que en Percona 5.7 es literalmente lo que ve el usuario, mientras que las de la Fase 9 dicen una frase que explica que paso. Cambiar un mensaje exige recrear la restriccion --Restriccion::comprobacion() crea, no reemplaza-- asi que es su propia iteracion, con su migracion y su vuelta atras. Se descubrio al escribir 9.14, que tuvo que afirmar por NOMBRE en vez de por mensaje en las veinte reglas del dinero
A12: T-68 | B12: Abierta | D12: El registro de decisiones y 16-RESPUESTAS-NEGOCIO.md no dicen lo mismo sobre que preguntas siguen abiertas. | E12: Antes de volver a contar preguntas abiertas | F12: Equipo de desarrollo | G12: Doc 16 da por respondidas en su §1 varias preguntas tempranas --Q-05 a Q-28-- y en 05-DECISION-LOG.md hay filas de ese rango que siguen sin tachar. Las dos cosas pueden ser ciertas a la vez --la pregunta gorda contestada y un detalle de diseno abierto-- pero nadie puede saberlo leyendo, y el registro de decisiones es el que manda (§94). Salio al construir las pestanas de tareas y preguntas del Excel de avance, que es la primera vez que alguien las conto. Hay que repasar ese rango una por una y cerrar en el registro las que doc 16 ya contesto, o dejar escrito que queda de cada una
A13: T-70 | B13: Abierta | D13: 16-RESPUESTAS-NEGOCIO.md se quedo viejo: veintiuna preguntas se respondieron el 2026-08-30 y no estan alli. | E13: Antes de volver a citarlo | F13: Equipo de desarrollo | G13: El registro de decisiones ya las tiene cerradas una por una; aquel documento sigue contando quince respuestas de agosto. O se actualiza, o se marca como historico de la primera tanda y se dice que el registro manda. Relacionada con T-68
A14: T-71 | B14: Abierta | D14: El logotipo esta compuesto con una tipografia de sistema, no con una de diseno. | E14: Cuando haya un logotipo disenado | F14: Equipo de desarrollo | G14: marca/01_Logo_Horizontal.svg y 02_Logo_Vertical.svg llevan el texto vivo con font-family="DejaVu Sans", y los SVG de public/img/brand/ son los contornos de esa misma composicion. Funciona y se ve bien, pero el wordmark no esta disenado: esta escrito con la tipografia por defecto del sistema que lo genero. No es urgente --la plataforma opera igual-- y deja de ser un problema tecnico en cuanto 9.17 permita subirlo: el dia que haya un logotipo de verdad se sube desde el admin y ya. Salio al contestar Q-30
A15: T-10 | B15: Resuelta | D15: RESUELTA (2026-08-26, iteracion 4.13). — El aviso al creador cuando cambian sus datos fiscales o su medio de pago. | E15: — | F15: Equipo de desarrollo | G15: Cierra la mitad que faltaba de BR-CREATOR-007 (🔴): la aprobacion interna existia desde 3.6 y 3.8, la NOTIFICACION no --«la pantalla se lo recuerda al operador para que lo haga a mano», que es otra forma de decir que no se hacia--. 390 pruebas, siete mutaciones en rojo, las seis puertas en verde con Deptrac incluido: que el grafo siga acilico ES parte del resultado. Ver docs/fase-4/4.13-AVISO-DE-CAMBIO.md
A16: T-11 | B16: Resuelta | D16: *(hecho en 3.14)* Rotar APP_KEY invalida las huellas de las cuentas bancarias. Los números siguen siendo recuperables (Crypt conserva APP_PREVIOUS_KEYS), pero la huella es un HMAC con esa clave: tras una rotación, la detección de cuentas repetidas (DEC-065) deja de funcionar sobre las filas viejas. | E16: Antes de la primera rotación de clave | F16: Equipo de desarrollo | G16: Hace falta un comando que las recalcule. No es un problema hoy y sí lo será el día de la primera rotación
... A25: T-20 | B25: Resuelta | D25: CERRADA DEL TODO (2026-08-25, iteracion 4.10). — La primera mitad la resolvio DEC-083. | E25: — | F25: Equipo de desarrollo | G25: El resto era el 1062 del recalculo cuando dos filas del MISMO creador convergen: con la clave rotada, dos medios de la misma cuenta llevan huellas distintas, uq_cpm_open_account no los ve y los dos entran; al recalcular convergen y la transaccion se cae con un Duplicate entry en crudo, dejando el recalculo sin hacer. Y este choque no se absorbe: reintentar da la misma huella y choca igual. Es el lado opuesto de DEC-087 --el valor no lo eligio el sistema, lo eligio la realidad-- y la respuesta es contar, no recalcular: dos medios abiertos del mismo creador que son la misma cuenta, y cual sobrevive depende de cual esta verificado y si tiene pagos detras. Ahora se ve en la revision, antes de escribir nada, comparando el estado DESPUES del recalculo --mirar solo las pendientes entre si dejaria pasar el caso mas probable, una fila vieja y una nueva-- y solo sobre las filas ABIERTAS. El 1062 que sobreviva a la carrera se traduce con Choque::esDe. Ver docs/fase-4/4.10-CONVERGENCIA-DE-HUELLAS.md
A26: T-21 | B26: Resuelta | D26: RESUELTA (2026-08-25). — «Vigente» exige valid_from <= CURDATE() (DEC-084), y el mensaje de aprobacion distingue «aprobado y vigente» de «aprobado, todavia NO rige» | E26: — | F26: Equipo de desarrollo
A27: T-22 | B27: Resuelta | D27: RESUELTA (2026-08-25). — La guarda de solicitudes deja de filtrar por estado —las unicas se apoyan en identity_gate, que no lo mira— y el mensaje distingue un duplicado administrativo de una persona en lista negra. | E27: — | F27: Equipo de desarrollo | G27: La de redes sociales comprueba ademas las cuentas propias, que era el caso frecuente
A28: T-23 | B28: Resuelta | D28: RESUELTA (2026-08-25). — DEC-086: middleware en el grupo web, pantalla de cambio, y tres reglas que hacen que sirva —la nueva distinta de la actual, se pide la actual, y sin permiso—. | E28: — | F28: Equipo de desarrollo | G28: La marca que se escribia desde 3.1 por fin significa algo
A29: T-24 | B29: Resuelta | D29: RESUELTA (2026-08-25). — max(1, ...) en el config. | E29: — | F29: Equipo de desarrollo | G29: Un comentario que dice «esto no puede pasar» y no lo impide es una nota, no una regla
A30: T-25 | B30: Resuelta | D30: RESUELTA (2026-08-25). La suite de PHPUnit se ejecuto por primera vez. — 228 pruebas, 695 aserciones. | E30: — | F30: Equipo de desarrollo | G30: Seis iteraciones (4.1–4.5 y los ~23 arreglos de las revisiones) solo se habian comprobado con suites SQL y puertas estaticas. Unico fallo real: tests/Feature/ExampleTest.php, la prueba de ejemplo de Laravel que afirma que / devuelve 200 cuando Route::redirect('/', '/panel') devuelve 302. Llevaba roja desde 1.1 y nadie lo sabia porque nada la ejecutaba: la puerta pruebas existe, pero el CI se instalo este mismo dia. RutasTest dice en su propio docblock que la *sustituye* — se escribio el reemplazo y no se borro el original. Se borra
A31: T-26 | B31: Resuelta | D31: RESUELTA (2026-08-25). Verificado el verificador. — Que 228 pruebas nunca ejecutadas salgan verdes a la primera es sospechoso, asi que se comprobo con tres mutaciones. | E31: — | F31: Equipo de desarrollo | G31: Dos se detectaron por la prueba que dice detectarlas (Vigencia::puedeRelevar() sin normalizar fechas → VigenciaTest; different:actual fuera → CambioPasswordTest). La tercera sobrevivio: devolver el where('le.status','active') a Cobertura::abiertaEnPais() dejaba las quince pruebas de 4.5 en verde. La suite SQL si lo veia —el disparador de no-solapamiento rechaza el INSERT— pero ninguna prueba comprobaba que la capa PHP lo evita ANTES, o sea que el operador recibiria un 45000 en crudo. Se anadio la prueba 16, que con la mutacion se pone roja
A32: T-27 | B32: Resuelta | D32: RESUELTA (2026-08-25, iteracion 4.11). — tools/pruebas/4.11-concurrencia.sh: dos clientes de verdad contra el mismo motor, sin un solo sleep de sincronizacion. | E32: — | F32: Equipo de desarrollo | G32: B pone innodb_lock_wait_timeout=1 y se afirma el 1205: mientras A tenga el bloqueo, B falla siempre, tarde lo que tarde la maquina; si no lo tiene, pasa. Los dos resultados son deterministas. Para saber que una sesion ya ejecuto se usan cerrojos con nombre: escribir una marca y buscarla en la salida no funciona porque el cliente bufferiza, y un GET_LOCK no es transaccional --se ve desde fuera aunque quien lo tomo siga con su transaccion abierta-- y se pregunta con SQL. Demuestra en el motor lo que hasta hoy estaba deducido y no medido: que el UPDATE que baja al principal no toma ningun bloqueo cuando el puesto esta libre, que por eso los dos llegan al INSERT, y que con el bloqueo de la fila del cliente se ponen en fila antes de escribir. Lleva su propio contraejemplo (con el puesto OCUPADO si espera), sin el cual la primera asercion saldria verde aunque el aparato no funcionase. Bateria: 812 (MariaDB) y 802 (MySQL 8), cero fallidas. El CI no hubo que tocarlo: los tres bloques leen SUITES desde DEC-076. Ver docs/fase-4/4.11-CONCURRENCIA.md
A33: T-28 | B33: Resuelta | D33: RESUELTA (2026-08-25). El paso verificar-pantallas.py del CI estaba roto desde que se instalo el workflow. — Apuntaba a stage/routes/web.php y stage/app, que es la disposicion del area de entrega y no la del repositorio: reventaba con un FileNotFoundError sobre una carpeta que en la maquina no existe. | E33: — | F33: Equipo de desarrollo | G33: No salia verde en falso --eso habria sido peor-- pero el paso no comprobaba nada y el mensaje no decia nada util. Las dos herramientas resuelven ahora la disposicion mirando cual existe. Y la puerta nueva sale con codigo 2 si recorre CERO archivos: contar que no hay problemas cuando lo que no hay es busqueda es el modo de fallo mas caro de una comprobacion automatica, y con este van tres en dos dias (T-25, la regex de verificar-fixturas.py, y esta)
A34: T-30 | B34: Resuelta | D34: RESUELTA (2026-08-25). — 09-NEXT-ITERATION.md llevaba desde el 21 de agosto diciendo «me detengo aqui; no hay codigo, no hay esquema y no hay wireframes». | E34: — | F34: Equipo de desarrollo | G34: Cuatro dias y 64 tablas despues, el documento cuyo unico trabajo es decir que viene ahora describia un proyecto que ya no existe. Reescrito entero: estado medido, que bloquea y a quien le toca, y la siguiente iteracion propuesta con su motivo. Y tres tareas mas estaban en el mismo estado: T-11, T-15 y T-16 decian «hecho en 3.14 / 3.11 / 3.12» y llevaban el marcador de ABIERTA. Es el mismo defecto que dejo T-12 en 📋 durante un mes estando resuelta
A35: T-31 | B35: Resuelta | D35: RESUELTA (2026-08-25). Dos de las seis puertas no se podian ejecutar del lado del contenedor, y por eso se entrego codigo con tres errores de PHPStan. — PHPStan y Deptrac no estaban instalados: packagist esta bloqueado desde aqui, asi que durante toda la sesion esas dos salieron «sin comprobar» mientras las otras cuatro pasaban. | E35: — | F35: Equipo de desarrollo | G35: Se resolvio trayendo los .phar por el puente desde la maquina del usuario --phpstan.phar (27 MB), deptrac.phar (1,5 MB), larastan y sus dependencias--, mas phpstan.neon y deptrac.yaml. Costo un rato: la limpieza de rutas colgantes del autoloader de T-25 habia dejado la entrada PSR-4 de Larastan con el array VACIO, y en PHP la ultima definicion de una clave gana, asi que rellenarla arriba no servia de nada --habia que rellenar la duplicada de abajo--. Es el mismo arreglo mordiendose la cola dos iteraciones despues. Ahora puertas corre las seis aqui. Las seis, en verde
A36: T-32 | B36: Resuelta | D36: RESUELTA (2026-08-25). — Los tres errores que PHPStan encontro en la maquina del usuario. | E36: — | F36: Equipo de desarrollo | G36: Dos eran de tipos puros --collect() sobre un mixed, y Collection<int, object> donde llega Collection<int, stdClass>, que no vale porque TValue no es covariante--. El tercero escondia un defecto de negocio: $antes salia de pluck() sin castear y $despues ya venia en int, asi que ['1'] !== [1] era SIEMPRE cierto y la bitacora anotaria un cambio de categorias cada vez que se guarda una marca, haya cambiado o no. No se pudo reproducir: depende de si PDO devuelve cadenas o enteros, y en el contenedor devuelve enteros. Queda fijado por MarcasTest, que documenta la intencion y dice explicitamente que no demuestra el fallo
A37: T-33 | B37: Resuelta | D37: RESUELTA (2026-08-25, iteracion 7.3). — ck_creq_deadline y ck_creq_permanence. | E37: — | F37: Equipo de desarrollo | G37: Los acotaba solo GuardarRequisitoRequest, y permanence_days es «cuanto debe seguir publicado»: de ahi sale lo que se le exige al creador y lo que se le promete al cliente. Un 100.000 --273 anos-- entraba por cualquier importacion, y lo que se rompe no es la base sino un acuerdo que nadie puede cumplir
A38: T-36 | B38: Resuelta | D38: RESUELTA (2026-08-26, iteracion 7.6b). — Ver DEC-126. | E38: — | F38: Equipo de desarrollo | G38: La pieza ya estaba: Cuentas::paraCreador() y Cuentas::paraInterno() se diferencian en tres argumentos, y eso es lo que se cobro la decision de 5.9 de poner esa clase en Identity en vez de en Creator
... A71: T-77 | B71: Resuelta | D71: RESUELTA (2026-08-31, hotfix de 9.12). El sembrador reescribia lo que una persona ya habia configurado, y ademas reventaba. | E71: 9.12 (hotfix) | F71: Equipo de desarrollo | G71: Reportada desde la instalacion: db:seed se paro con un 45000 porque updateOrInsert movia el valid_from de la fila ABIERTA de fx_official_sources encima de un periodo cerrado a mano (T-73 desde el otro lado). Lo que el error tapaba era peor: el sembrador murio en la linea 71 de 700, asi que los proveedores de 9.17d y los tipos de comprobante de 9.12 no llegaron a entrar. Y de fondo: cada db:seed --lo que el runbook manda tras cada migracion-- devolvia a fabrica el nombre, lema, colores y tipografia de la marca y la direccion de la sociedad, REGENERABA sus uuid y reactivaba fuentes y proveedores apagados a proposito. Regla nueva: lo que una persona puede cambiar se siembra si falta y no se toca si esta (sembrarSiFalta); donde hay vigencia, el periodo empieza el dia siguiente al ultimo cierre. 5 pruebas verificadas en rojo sin el arreglo.
A72: T-78 | B72: Abierta | C72: Media | D72: Convertir a route() las 390 direcciones escritas a mano en las pruebas. | E72: Al tocar cada archivo | F72: Equipo de desarrollo | G72: La mudanza a /backoffice fue gratis en la aplicacion --ni una URL a mano-- y costo 390 sustituciones en tests/, porque una prueba que escribe /clientes FIJA la URL. Se corrigieron con un guion que sale de la lista real de rutas movidas, y la primera pasada dejo dos fuera (/bitacora?tipo=..., con cadena de consulta) que cazo la suite. Mientras sigan siendo cadenas, la proxima mudanza costara lo mismo.

Sheet Preguntas
A1: Preguntas de negocio (Q-XX). Una pregunta abierta es trabajo que NO se puede hacer hasta que alguien decida. Las respondidas conservan la pregunta original detrás de la respuesta. Fuente: docs/05-DECISION-LOG.md.
A2: ID | B2: Estado | C2: Prioridad | D2: Que hay que decidir | E2: Cuando hace falta | F2: Quien la desbloquea | G2: Detalle
A3: Q-47 | B3: Abierta | D3: Abierto por la iteración 3.6. | E3: Iteración de rechazo de creadores | F3: Tu (decision de negocio) | G3: BR-CREATOR-014 fija un periodo de gracia de 30 días antes de rechazar a un creador por falta de datos fiscales, y dice «configurable». ¿Configurable globalmente (una constante de despliegue) o por creador, como payment_term_days? No lo invento: son dos modelos de datos distintos. Hasta que se responda, el periodo de gracia no está implementado
A4: Q-50 | B4: Abierta | D4: ¿campaign_creators, agreement_amendments, domain_events y status_transitions son evidencia? | E4: Al construir el módulo de campañas | F4: Tu (decision de negocio) | G4: Se quedaron fuera de 3.12 a propósito. campaign_creators lleva agreed_amount —el precio pactado, congelado—, y borrar una participación borraría el precio con ella; pero el módulo de campañas no está construido y decidir ahora si una participación se borra o se cancela sería adivinar. Los otros dos son rastros de auditoría de alto volumen, donde puede hacer falta purga por antigüedad. Que lo decida la iteración que los construya, con el caso de uso delante
A5: Q-52 | B5: Abierta | D5: ¿Un cliente debería exigir contacto principal de facturación antes de poder estar active? | E5: Facturación (F9) | F5: Tu (decision de negocio) | G5: Hoy nada lo obliga: contacts no tiene regla que exija un principal de ningún tipo, y un cliente puede activarse sin un solo contacto. Cuando llegue la facturación habrá que saber a quién se le manda la factura, y descubrirlo entonces significa perseguir clientes ya activos. La ficha lo avisa en ámbar y no lo impide, porque convertirlo en requisito es una decisión de negocio: bloquear el alta de un cliente por un dato que a veces llega después tiene su propio coste. Si la respuesta es sí, el sitio es la activación del cliente, no contacts
A6: Q-53 | B6: Abierta | D6: ¿El mismo correo repetido dentro del mismo cliente y tipo es un error? | E6: Importación de clientes | F6: Tu (decision de negocio) | G6: contact_email no es único a propósito: es un canal comercial y puede compartirse (facturacion@cliente.com para varias personas), a diferencia de users.email, que es la identidad de acceso y sí lo es. Pero dos contactos con el mismo correo, el mismo cliente y el mismo tipo parece captura duplicada más que reparto. No se ha añadido regla: una validación que solo vive en el formulario se la salta cualquier importación o INSERT de mantenimiento. Si se decide que es error, el sitio es el esquema
A7: Q-54 | B7: Abierta | D7: ¿Se puede corregir un periodo fiscal ya CERRADO? | E7: Primera correccion real de un histórico | F7: Tu (decision de negocio) | G7: DEC-078 dice que no: sólo se corrige el vigente. Cubre el caso normal —el cliente cambió de razón social, y eso es un periodo nuevo, no una reescritura— pero deja fuera el RUC tecleado mal que no se detecta hasta meses después, cuando el periodo ya se cerró. Hoy eso se arregla en base de datos. Si se decide permitirlo por pantalla, la forma es la de la anulación de perfiles fiscales de creador (3.11): permiso propio, motivo escrito y rastro de quién. Lo que no puede ser es un UPDATE normal
A8: Q-55 | B8: Abierta | D8: ¿Se valida el formato del documento fiscal por país? | E8: Alta de clientes en el segundo país | F8: Tu (decision de negocio) | G8: Hoy no: tax_id_number acepta cualquier cosa de hasta 40 caracteres y la pantalla avisa de que no se comprueba. Escribir una tabla de expresiones regulares (11 dígitos para un RUC peruano, dígito verificador del NIT colombiano…) es fácil y es una trampa: en cuanto una esté mal o falte un país, el sistema rechaza un documento válido y no hay forma de meterlo, que es peor que aceptar uno malo —eso se detecta al facturar—. Si se hace, tiene que ser dato de catálogo por país y editable, no código
A9: Q-56 | B9: Abierta | D9: .deliverable_versions es evidencia? | E9: 8.1 | F9: Tu (decision de negocio) | G9: Hoy se puede borrar fisicamente. El criterio de 3.12 para entrar en la lista de no_delete es «la fila es EVIDENCIA de algo que paso, y de ella depende dinero o una obligacion legal», y una version entregada cumple los dos: es lo que el cliente aprueba y lo que dispara el pago. Borrar la version 1 despues de aprobar la 2 reescribe la historia de una ronda de correccion que se facturo. No se ha cambiado en 8.1 porque 3.12 eligio dieciocho tablas de una lista y no hay documento que diga si esta se considero y se descarto o si simplemente no estaba (T-29): decidirlo con el documento delante, no de memoria. Nota practica si se decide que si: la suite de 8.1 dejaria de poder limpiar lo suyo, que es el caso «TOZUDAS» que verificar-fixturas.py ya documenta, y la propia suite lo dice en el sitio donde se rompera
A10: Q-57 | B10: Abierta | D10: .Donde acaba la linea del cargo por una ronda de correccion de mas? | E10: 8.3 | F10: Tu (decision de negocio) | G10: Hoy queda la DECISION en content_reviews --se cobra o se absorbe, quien lo autorizo y cuando-- y la pantalla de entregables la ensena como pendiente de facturar. No va a campaign_costs a proposito (DEC-135). Cuando exista facturacion (F9) habra que decidir si es una invoice_lines que se genera sola, un concepto aparte, o algo que finanzas teclea leyendo esta lista. Se decide con invoice_lines delante, no de memoria, y hasta entonces la lista de la pantalla es el registro
A11: Q-58 | B11: Abierta | D11: .Se puede reabrir un entregable ya PUBLICADO o VERIFICADO? | E11: 8.2 | F11: Tu (decision de negocio) | G11: Hoy no: tg_cvw_entregable_abierto cierra published, verified y cancelled sin excepcion, y solo deja reabrir lo approved. No hay diferencia practica todavia porque publications se llena en 8.6, pero cuando la haya habra que decidir que pasa con la evidencia archivada (8.7) y con la permanencia minima (8.8) de un post que se retira para rehacerlo. Se decide con publication_evidence delante
A12: Q-59 | B12: Abierta | D12: ¿La ventana de permanencia se alarga por los dias que el post estuvo caido? | E12: Con el contrato del creador | F12: Tu (decision de negocio) | G12: Hoy no: reponer devuelve la publicacion a verified y permanence_until no se toca. Si el post estuvo tres dias fuera, la marca perdio tres dias de exposicion y el creador cumple igual. Alargarla seria lo justo y alargarla por mi cuenta seria inventarme una clausula, asi que va con el texto del contrato, junto a T-09
A13: Q-60 | B13: Abierta | D13: ¿deliverables.revision_rounds_used deberia existir? | E13: Facturacion (F9) | F13: Tu contador | G13: Es una desnormalizacion que anadio 8.3. Las revisiones son append-only (tg_cvw_inmutable), asi que el numero exacto se deriva con un COUNT(*) sobre content_reviews donde consumes_round = 1, y entonces no hay contador que desincronizar ni que proteger --tg_del_rondas sobraria--. A cambio, cada lectura del techo cuesta un JOIN. Se decide cuando ese numero sea una linea de factura
A14: Q-61 | B14: Abierta | D14: ¿Como se marca una ronda de mas como facturada? | E14: Facturacion (F9) | F14: Tu (decision de negocio) | G14: content_reviews es append-only desde 8.3 --tg_cvw_inmutable bloquea todo UPDATE-- asi que no se le puede poner un invoiced_at. El enlace tiene que ir al reves: de la linea de factura a la revision. Mientras no exista, rondasCobrables() devuelve todas las autorizadas y la pantalla lo dice con esas palabras. Lo decide quien construya la facturacion, que es quien sabe que forma tiene una linea
... A37: Q-21 | B37: Resuelta | D37: RESPONDIDA (2026-08-30). | E37: Respondida | F37: Tu contador | G37: Resuelta por Q-03: no hay proveedor intermedio, se timbra directo con SUNAT y todo es configurable. *Pregunta original:* ¿El proveedor de facturación electrónica permite una cuenta por sociedad, o exige contrato separado por RUC?
A38: Q-22 | B38: Resuelta | D38: 100% interna | E38: — | F38: Tu (decision de negocio)
A39: Q-23 | B39: Resuelta | D39: RESPONDIDA (2026-08-30). | E39: Respondida | F39: Tu (decision de negocio) | G39: La gamificacion premia con reconocimiento. *Pregunta original:* ¿Qué desbloquea realmente el nivel? Define si la gamificación es reconocimiento o política comercial.
A40: Q-24 | B40: Resuelta | D40: RESPONDIDA (2026-08-30). | E40: Respondida | F40: Tu (decision de negocio) | G40: Por ahora no hay premios en dinero. Habra un catalogo de premios canjeables con XP --viajes, cosas-- configurable desde el admin. Ver DEC-194. *Pregunta original:* ¿El XP podrá convertirse en dinero o bienes? Si no, el problema fiscal y legal se reduce drásticamente.
A41: Q-25 | B41: Resuelta | D41: RESPONDIDA (2026-08-30). | E41: Respondida | F41: Tu (decision de negocio) | G41: El hito de consolidacion del referido es la primera campana completada. *Pregunta original:* ¿Cuál es el hito de consolidación del referido: aprobación, o primera campaña completada?
A42: Q-26 | B42: Resuelta | D42: RESPONDIDA (2026-08-30). | E42: Respondida | F42: Tu (decision de negocio) | G42: Absorbida por Q-24: los retos internos premian con XP canjeable en el catalogo, no con dinero. *Pregunta original:* ¿Los retos internos pagarán en dinero, producto o acceso prioritario?
A43: Q-27 | B43: Resuelta | D43: RESPONDIDA (2026-08-30). La Academia del creador QUEDA | E43: Respondida | F43: Tu (decision de negocio) | G43: , y cada modulo es configurable desde el admin. Ver DEC-196. *Pregunta original:* ¿Hay presupuesto para la Academia del creador? Es contenido, no software.
A44: Q-29 | B44: Resuelta | D44: RESPONDIDA (2026-08-30). | E44: Respondida | F44: Tu (marca) | G44: La tipografia y la identidad visual se configuran desde el admin, no se eligen en el codigo. La propuesta (Sora + Plus Jakarta Sans + IBM Plex Mono) queda como valor de partida y se cambia sin tocar codigo (DEC-190). *Pregunta original:* ¿Se aprueba la propuesta tipográfica (Sora + Plus Jakarta Sans + IBM Plex Mono), o hay una tipografía corporativa ya comprada?
A45: Q-30 | B45: Resuelta | D45: RESPONDIDA (2026-08-30). | E45: Respondida | F45: Tu (marca) | G45: El kit de marca si esta en el repositorio (marca/), pero al mirarlo para contestar salio algo que conviene saber: el logotipo horizontal y el vertical llevan el texto vivo con font-family="DejaVu Sans" --una tipografia de sistema, no una elegida-- y los derivados de public/img/brand/ son los contornos de esa misma. No hay un maestro editable con tipografia de diseno. La respuesta es la correcta: se hace configurable y se sube desde el admin cuando exista uno de verdad. Ver T-71. *Pregunta original:* ¿Existe versión editable del wordmark (AI/Figma) con la tipografía real que usó el diseñador? Si la hay, sustituye a mis contornos.
A46: Q-31 | B46: Resuelta | D46: RESPONDIDA (2026-08-30). | E46: Respondida | F46: Tu (decision de negocio) | G46: Configurable desde el admin: la marca de la plataforma es un dato, no un archivo del repositorio. *Pregunta original:* ¿Se sustituye el kit original por las versiones corregidas, o conviven? Recomiendo sustituir: dos favicon distintos garantizan que alguien use el roto.
A47: Q-33 | B47: Resuelta | D47: RESUELTA (negocio, 2026-08-22): — todo creador debe tener datos fiscales legales y vigentes. | E47: — | F47: Tu (decision de negocio) | G47: No hay pago informal. Sin ellos no se activa; si no se regulariza, se rechaza. → BR-CREATOR-013
A48: Q-34 | B48: Resuelta | D48: RESPONDIDA (2026-08-30). | E48: Respondida | F48: Tu (decision de negocio) | G48: Colombia no es prioritaria en esta primera fase. *Pregunta original:* ⚠️ ADOPTADA MI RECOMENDACIÓN, contraria a lo que dijiste — revísala. Dijiste *"DIAN directo"*. Recomiendo empezar con un proveedor tecnológico certificado y dejar la habilitación propia para después. Motivo: habilitarse como proveedor propio ante la DIAN es un proceso de meses con pruebas de conformidad, y bloquearía la operación en Colombia mientras tanto. Con proveedor se factura en semanas y la habilitación propia se hace en paralelo sin urgencia. Si tu prioridad es no depender de terceros, dilo y lo revierto
A49: Q-35 | B49: Resuelta | D49: ADOPTADA (recomendación, 2026-08-22): | E49: — | F49: Tu (decision de negocio) | G49: el cliente asume producto y logística, y ambos se registran como *Direct Cost* de la campaña e impactan el margen (BR-FIN-011, que ya lo decía). El creador asume el costo de creación, no el del producto — eso ya lo confirmaste. El producto no se devuelve salvo pacto expreso en la campaña
A50: Q-36 | B50: Resuelta | D50: RESUELTA (negocio, 2026-08-22): — todo por Google Workspace por ahora — el volumen actual no llega a 100 correos. | E50: Configuración | F50: Tu (decision de negocio) | G50: El proveedor transaccional queda como opción de configuración, no como código nuevo: el correo es una conexión de integración con purpose = transactional_mail (docs/12), así que cambiarlo es editar una conexión en el back-office. Disparador para cambiar, escrito ahora para no discutirlo luego: cuando un solo envío de campaña supere ~200 destinatarios en un día, o cuando empiecen a salir avisos de pago. Ver docs/fase-2/2.10 §8
... A60: Q-63 | B60: Resuelta | D60: RESPONDIDA (2026-08-30). | E60: Respondida | F60: Tu contador | G60: NO se fija un lado del tipo de cambio en el codigo: se configura desde el admin, y por tipo de transaccion --lo que se paga a un creador, lo que se le cobra a un cliente, un gasto-- porque no tienen por que usar el mismo. Ver DEC-195. *Pregunta original:* 🔴 .Que LADO del tipo de cambio se aplica a cada operacion: compra, venta o media? SUNAT publica los dos y 9.1 los guarda separados (side), sin valor por defecto a proposito, para que nadie lo elija sin querer (DEC-159). Es una decision contable y no tecnica: cada eleccion da un margen distinto para los mismos hechos, y el dia que se elija cambian todos los margenes historicos a la vez. Bloquea de verdad: 9.10a y 9.10 agrupan por moneda en vez de sumar por esto (DEC-180), y la rentabilidad no da porcentaje cuando hay dos monedas (DEC-185). Se abrio en 9.1 y esta fila nace en 9.15

Sheet Decisiones
A1: Las decisiones de diseño y de negocio (DEC-XXX) del registro. Una decisión es una elección que ya se tomó y que el sistema respeta; «Propuesta» significa que está razonada y construida pero sin firma formal tuya. Fuente: docs/05-DECISION-LOG.md. Las más recientes arriba.
A2: ID | B2: Estado | C2: Prioridad | D2: Qué se decidió | E2: Dónde se aplicó | F2: Detalle y por qué
A3: DEC-242 | B3: Decidida | D3: El contacto de una marca es una FILA, no un correo | E3: 9.21c | F3: Hoy el correo esta en «log» --no sale del servidor-- asi que una instalacion con el SMTP a medio configurar perderia cada contacto sin que nadie se entere. Un correo que no llega no deja rastro; una fila si, y ademas se puede contar. El aviso por correo va encima de la fila, no en lugar de ella.
A4: DEC-243 | B4: Decidida | D4: Misma forma que creator_applications, y solo lo abierto ocupa la puerta | E4: 9.21c | F4: Son el mismo problema: alguien de fuera deja sus datos y alguien de dentro los atiende. Copiar la forma que ya funciona sale mas barato que inventar la segunda, y quien conozca una bandeja conoce las dos. Lo cerrado deja el hueco libre: quien vuelve a escribir el ano que viene es un contacto nuevo de verdad, no un duplicado.
A5: DEC-244 | B5: Decidida | D5: Descartar no es borrar, y convertir se hace en dos pasos | E5: 9.21c | F5: De esta tabla salen «.de donde salio este cliente?» y «.cuantos descartamos y por que?»; borrar se lleva las dos por delante. Descartar exige un motivo de al menos diez caracteres. Y convertir exige decir en que cliente: crear ese cliente se sigue haciendo en su pantalla de siempre, porque duplicar el formulario seria tener dos sitios donde se crea un cliente.
A6: DEC-238 | B6: Decidida | D6: / habla a las MARCAS y /creadores a los creadores | E6: 9.21b | F6: Es un mercado de dos lados y el lado que PAGA se pone en la puerta: una portada que abre reclutando creadores se lee como «agencia buscando talento». Los creadores llegan por un enlace, no por la home. Las dos se enlazan entre si. El argumento en contra queda escrito: si el cuello de botella es tener creadores, el trafico que hace falta primero es el suyo; aun asi la home no cambia, porque moverla despues cuesta posicionamiento.
A7: DEC-239 | B7: Decidida | D7: El texto de la portada es un dato, y cuelga de la marca | E7: 9.21b | F7: DEC-190 en el sitio donde mas se nota: la marca del panel la ve quien ya entro; esto lo ve quien todavia esta decidiendo si te escribe. landing_pages lleva platform_brand_id: es UNA columna sobre el eje en el que el producto esta construido --distinto de las asignaciones de tres ejes de 9.17d, que resolvian un problema inexistente--. Dos paginas y no un gestor de contenidos: cada una tiene su formulario y su publico, asi que son codigo.
A8: DEC-240 | B8: Decidida | D8: La postulacion publica escribe en creator_applications, que ya existia | E8: 9.21b | F8: Existe desde la Fase 2 con source por defecto «landing», su bandeja y su unica de una solicitud abierta por correo; faltaba la landing que escribiera. Un formulario publico que escribe lleva throttle:5,1 y un campo trampa que una persona no ve; si viene lleno se contesta «gracias» y no se escribe nada. Nada de CAPTCHA: barrera para quien lee con dificultad y tramite de segundos para quien automatiza. Vive en Creator y no en Core: T-74 aplicada antes de romperla.
A9: DEC-241 | B9: Decidida | D9: Sin portada se va al acceso, no a un 404 | E9: 9.21b | F9: Una instalacion recien migrada no tiene contenido que ensenar, y eso no puede ser un error en la cara de un visitante: es exactamente lo que habia antes. Lo mismo al apagar una portada desde el admin, que es una decision de contenido y no una averia.
A10: DEC-236 | B10: Decidida | D10: Todo lo que exige sesion vive bajo /backoffice | E10: 9.21a | F10: Lo vio el negocio antes de escribir una linea de la landing: /creadores tiene que ser la puerta PUBLICA de los creadores, y descubrirlo despues de publicar habria roto enlaces ya compartidos. Dentro entra todo lo que pide sesion sea de quien sea; lo que cada uno ve lo siguen decidiendo sus permisos. Costo una linea porque docs/08 prohibe escribir URLs a mano en las vistas: comprobado, cero resultados en app/, resources/ y config/.
A11: DEC-237 | B11: Decidida | D11: Veintiuna rutas se quedan fuera, y cada una con su motivo escrito | E11: 9.21a | F11: El acceso y la recuperacion son la puerta; la invitacion y la aprobacion llegan por enlace con token a alguien que no tiene cuenta; el logotipo y el favicon los pinta la pantalla de acceso. Dos comparten primer segmento con algo que si se mudo: /contrasena frente a /contrasena/nueva, y /marca frente a /marca/logo. La lista vive en una prueba que recorre todas las rutas con nombre.
A12: DEC-233 | B12: Decidida | D12: La configuracion tiene UNA sola puerta, y el menu lateral solo lleva trabajo | E12: 9.20 | F12: Nueve pantallas estaban dos veces --sueltas en el menu y dentro de /configuracion--, asi que entrar desde el panel dejaba al usuario en una pantalla que se veia igual que Campanas y con el menu marcando otra entrada. El menu queda en tres grupos --Operacion, Finanzas, Registros-- mas Ajustes: Configuracion, y un grupo del que no se puede ver nada desaparece entero.
A13: DEC-234 | B13: Decidida | D13: El orden de los grupos es una decision y vive en el registro, no en la plantilla | E13: 9.20 | F13: revision() ordena por URGENCIA, que es lo correcto para una lista de avisos y lo peor para una navegacion: «Fiscal y facturacion» saldria arriba o abajo segun que falte hoy, y un sitio que cambia de forma segun el dia no se aprende. Por lo mismo, que rutas son configuracion sale de Preparacion::rutas() y no de la plantilla.
A14: DEC-235 | B14: Decidida | D14: Los catalogos son configuracion, con portada propia | E14: 9.20 | F14: Los seis colgaban del menu bajo un titulo que no era un sitio: era una etiqueta. Ahora son un area con portada --cuantas filas y cuantas activas-- y su aviso: una lista sin ninguna fila activa sale en rojo, porque un catalogo vacio no da error, deja un desplegable vacio. La pantalla de cada catalogo no se mueve.
... A56: DEC-191 | B56: Decidida | D56: La retencion se calcula HACIA ATRAS desde el neto pactado, y se compara con un umbral de rentabilidad. | E56: 9.16 | F56: Con el creador se pacta lo que VA A RECIBIR --«te pago 100»--; el sistema calcula el bruto que hay que provisionar con la tasa configurada (29,5% por defecto, Q-13/Q-40): bruto = neto / (1 - tasa), o sea 141,84 para 100 netos, de los que 41,84 son retencion. Tres campos y no uno: neto pactado, tasa aplicada (por defecto la del admin, editable en el trato) e importe bruto. Encima va un umbral de rentabilidad minima configurable: con el bruto como costo, la pantalla dice cual es el ingreso mas bajo que hace aceptable esa participacion, y avisa antes de cerrar el trato --no despues--. La tasa, el umbral y la base sobre la que se mide el umbral (sobre costo o sobre ingreso: no dan el mismo numero) salen del admin
A57: DEC-190 | B57: Decidida | C57: Critica | D57: PRINCIPIO RECTOR: la plataforma es WHITE LABEL y todo se configura desde el admin. | E57: 9.16 | F57: Nada de reglas de negocio quemadas en el codigo: ni la razon social, ni el RUC, ni el representante legal, ni la direccion, ni el ubigeo, ni las tasas, ni los plazos, ni los correlativos, ni las credenciales de ninguna API. Lo que el codigo aporta es la REGLA; el VALOR sale de la configuracion. Y una configuracion sin valor no bloquea: se siembra con un valor de partida y se avisa con su prioridad --rojo si es delicado y sigue de fabrica, ambar si conviene revisarlo--. Esto corrige el criterio con el que se habian tomado varias decisiones anteriores --3.5 dejaba el sistema sin arrancar hasta que alguien corriera un comando, y varias preguntas de negocio se plantearon como «elige una y la quemo» cuando la respuesta correcta era «las dos, y que se elija en el admin»--. Toda decision anterior que fije un valor en el codigo queda sujeta a revision bajo este principio (T-69)
A58: DEC-189 | B58: Decidida | D58: Las 23 rutas sin permiso se escriben, con su motivo, en RUTAS-ABIERTAS. | E58: 9.14b | F58: Hasta hoy nada distinguia «es publica a proposito» --entrar, recuperar la contrasena, los enlaces firmados de 7.6 y 8.5-- de «se le olvido el middleware a alguien». verificar-muro.py comprueba que tres sitios digan lo mismo: la lista, routes/web.php y la constante de MuroTest; no se pueden fundir porque una la lee Python sin Laravel y otra PHPUnit, y tres copias es como se pierde una (SUITES, 3.12). Al CI: una ruta nueva sin permiso que no este escrita lo pone en rojo. De paso se cerraron dos puertas que no eran nuestras: storage.local y storage.local.upload, que registra el framework con serve => true sobre el disco privado. No eran una fuga --exigen URL firmada-- pero la aplicacion no genera ninguna, asi que no servian para nada; y ninguna lectura del codigo las habria encontrado, porque no estan en ningun archivo de rutas
A59: DEC-188 | B59: Decidida | D59: El muro se prueba recorriendo TODAS las rutas, no las que uno recuerda. | E59: 9.14b | F59: MuroTest pide las 145 rutas con nombre como creador, como usuario de cliente y como autenticado sin rol, y exige que ninguna se abra --371 aserciones, y el muro aguanta--. Una pantalla nueva entra sola en la prueba. Las afirmaciones dirigidas que ya habia (DEC-172, DEC-179, DEC-181) comprueban lo que alguien se acordo de mirar; el fallo que de verdad paso --5.9, la portada enseñando los totales internos a cualquier autenticado-- no lo habria cazado ninguna. Lo permitido se escribe en positivo: una lista de lo permitido crece solo cuando alguien la toca a proposito. Se admite un 404 porque SubstituteBindings corre antes del middleware --con un id inventado la ruta contesta antes de llegar al permiso-- y para que no sea el escondite de la prueba se exige que mas de 80 rutas contesten 403 de verdad
A60: DEC-187 | B60: Decidida | D60: Una suite de QA se construye SU caso y no reusa el de nadie. | E60: 9.14 | F60: La primera version de 9.14 reusaba lo que dejaban las suites anteriores, como hace 9.6, y se puso amarilla dos veces por motivos opuestos: corriendo sola porque no habia asientos, y corriendo la bateria entera porque para cuando llega el unico devengo pagable ya esta liquidado por 9.6 y las dos participaciones de la semilla estan ocupadas. Ahora crea su campana, su participacion y su devengo. Una suite de QA que depende del orden mide el orden, no la regla
A61: DEC-186 | B61: Decidida | D61: Nace verificar-cobertura-sql.py: que regla de la base no ha contestado NUNCA a nadie. | E61: 9.14 | F61: Los verificadores que ya habia comprueban que la regla EXISTA y que sea la misma en los dos motores; ninguno comprobaba lo unico que importa el dia que falle: que alguien se lo haya preguntado. Medido: de las 317 reglas del esquema, 167 no aparecian en ninguna suite ni en ninguna prueba --el 53%--. No significa que esten mal: significa que nadie lo sabe. Una regla que nunca se ha probado no es una regla, es una intencion escrita en DDL. Va a correr-todo.sh y al CI con trinquete (MUDAS-BASE), asi que una regla nueva sin asercion pone el CI en rojo. La pregunta salio de 9.10a, donde campaign_costs llevaba dos semanas con cinco restricciones verdes en todos los verificadores y CERO filas
A62: DEC-185 | B62: Decidida | D62: El porcentaje de margen solo se da cuando todo esta en una moneda, y si no, se dice por que. | E62: 9.10 | F62: Convertir exige elegir compra, venta o media (Q-63) y cada eleccion da un margen distinto para los mismos hechos; el dia que se elija cambian ademas todos los margenes historicos a la vez. Cuando falta, la pantalla escribe el motivo con palabras --«esta campana tiene importes en PEN y USD…»-- y no deja un hueco: quien mira una pantalla donde falta un numero necesita saber si falta porque no lo hay o porque no se puede calcular, y son dos conversaciones distintas. Tampoco hay total por sociedad: el ingreso de hoy es el DECLARADO y no el facturado (9.9), y sumar precios declarados por sociedad se parece a un estado de resultados sin serlo
A63: DEC-184 | B63: Decidida | D63: Los canjes salen en la lista, marcados, y fuera de todo total. | E63: 9.10 | F63: Su ingreso es cero POR DECISION (7.2), asi que su margen es siempre negativo: el producto y el envio se gastaron igual. Promediarlos hace que la cartera entera parezca peor por un motivo que fue deliberado. Pero se enseñan con su costo, porque un canje tambien cuesta dinero y ese era justo el numero que nadie tenia. Queda fuera del total una segunda clase de campana: la que tiene gastos en OTRA moneda, cuyo margen en la moneda del grupo esta incompleto --y sumar un numero incompleto lo vuelve invisible--. Y la cabecera dice cuantas quedaron fuera y por que: un total que excluye filas sin contarlas engaña por omision
A64: DEC-183 | B64: Decidida | D64: Compromiso::margen() se BORRA, no se arregla. | E64: 9.10 | F64: Vivia en Campaign desde 7.7 y devolvia revenue_amount menos lo comprometido con creadores: no restaba producto, envios ni produccion, y desde 9.10a esos gastos ya se anotan, asi que el numero habria ido empeorando con cada gasto cargado sin que la pantalla se enterara. No se arregla donde estaba porque campaign_costs es de Finance y deptrac no deja que Campaign la conozca --misma frontera que el devengo de 9.4--. Y se borra en vez de dejarse por si acaso: un metodo que calcula un numero incompleto y se llama margen() es una trampa para quien lo encuentre dentro de seis meses. De paso, SeguimientoController deja de pasar un importe y pasa un booleano mas un enlace: ningun numero interno cruza ya hasta la plantilla, que es BR-SEC-001 un paso mas alla
A65: DEC-182 | B65: Decidida | D65: El costo del creador entra al DEVENGARSE, no al pagarse. | E65: 9.10a | F65: La deuda existe desde que acepta (9.4) y su importe esta congelado desde 7.5; esperar al pago haria que una campana terminada en marzo pareciera rentabilisima hasta el lote de abril. Sale del libro mayor y no de campaign_creators, porque el libro es quien sabe que devengos siguen vivos: uno anulado ya no se debe. Y no es Compromiso::comprometido(), que cuenta tambien a los shortlisted: alli es correcto --su trabajo es proteger el presupuesto ANTES de invitar-- y aqui contaria dinero de gente que todavia puede decir que no
A66: DEC-181 | B66: Decidida | D66: Cargar gastos no es ver el margen: campaign_manager pierde campaign.view_margin. | E66: 9.10a | F66: Quien lleva una campana anota lo que se gasta y ve cuanto lleva gastado; el margen --lo que se gana-- es una cifra de direccion, y el camino por el que un numero interno acaba en un correo a un cliente empieza siempre por alguien que podia verlo sin necesitarlo (BR-SEC-001, 🔴). No nace un permiso nuevo para el margen: campaign.view_margin ya existe y hace eso, y un segundo permiso para el mismo secreto es la forma clasica de que un dia se conceda el que nadie mira. Lo que nace es finance.cost.manage, que es la capacidad que de verdad no existia. Y la revocacion va en la MIGRACION y no en el seeder (T-64)
A67: DEC-180 | B67: Decidida | D67: El gasto de una campana se agrupa por moneda: no se suma. | E67: 9.10a | F67: Un envio se paga en dolares y la campana se cobra en soles; sumarlos exige un tipo de cambio, y cual --compra, venta o media-- es una decision contable que sigue abierta (Q-63) y que da tres margenes distintos para los mismos hechos. Es la misma decision que el saldo del creador en 9.8, por el mismo motivo. Un numero que parece exacto y depende de una eleccion que nadie ha hecho es peor que dos numeros separados
A68: DEC-179 | B68: Decidida | D68: Al creador se le avisa al CONFIRMAR y al DEVOLVER, no al enviar. | E68: 9.7 | F68: Avisar al enviar es avisar de una intencion: si el banco lo rechaza, el creador ya cree que cobro, y el segundo correo desmiente al primero --dos correos que se contradicen cuestan mas confianza que un correo que llega un dia mas tarde--. Ninguno de los dos lleva numero de cuenta ni referencia bancaria: un correo se lee en pantallas ajenas y se reenvia, y para saber que le pagaron no hace falta ver su cuenta; es la misma decision que los avisos de 4.13. Y lo que faltaba en payouts no eran los estados --estan desde la Fase 2-- sino el GRAFO: sin tg_payout_estado, un pago saltaba de pending a confirmed sin haber salido nunca, y uno devuelto volvia a sent con un UPDATE, borrando que el banco lo habia rechazado. Mismo agujero que ledger_entries tenia antes de 9.3
A69: DEC-178 | B69: Decidida | D69: Un pago devuelto por el banco NO deshace el devengo. | E69: 9.7 | F69: El devengo se queda en paid porque se pago: lo que fallo fue la transferencia, no el trabajo --y paid es terminal desde DEC-169--. La correccion es un asiento de payment_reversal que apunta al asiento de pago original (BR-FIN-002), positivo, asi que devuelve el saldo; los dos hechos quedan escritos --se pago, y volvio-- en vez de que el segundo borre al primero. Nace accrued porque ck_ledger_estado_inicial no admite nacer pagable --a pagable se LLEGA-- y se mueve a payable en la misma operacion: el creador ya cumplio, y su dinero no tiene que esperar a que alguien se acuerde de revisarlo. Si el pago no tuviera asiento en el libro mayor, devolver() falla en voz alta en vez de dejar el saldo diciendo que cobro algo que no tiene
... A160: DEC-087 | B160: Decidida | D160: Un 1062 se absorbe o se cuenta segun quien eligio el valor, y hay que NOMBRAR el indice para absorberlo. | E160: 4.6 | F160: Si el valor lo calculo el sistema —el slug de una marca— el choque se recalcula y se reintenta en silencio. Si lo escribio la persona —un RUC, el nombre de una marca— tiene que llegar arriba con palabras. App\Shared\Database\Choque obliga a elegir: reintentar() exige el nombre del indice y vuelve a lanzar cualquier otro a la primera, porque un catch (QueryException) a secas absorberia el RUC repetido igual que el slug. Tres intentos como tope: un bucle sin tope convierte un indice mal entendido en una peticion eterna. El nombre se lee cortando por el ultimo punto —MySQL 8 antepone la tabla y Percona 5.7 no—, comprobado contra los dos motores
A161: DEC-086 | B161: Decidida | D161: La contraseña temporal deja de ser válida en el primer acceso
A162: DEC-085 | B162: Decidida | D162: La bitácora la protegen dos usuarios de base de datos, no el esquema
A163: DEC-084 | B163: Decidida | D163: «Perfil fiscal vigente» exige que ya haya empezado
A164: DEC-083 | B164: Decidida | D164: «Cuenta compartida» se calcula al leer, no se guarda
A165: DEC-082 | B165: Decidida | D165: Las sociedades del grupo las gestiona sólo admin
A166: DEC-081 | B166: Decidida | D166: Dar de baja una sociedad cierra sus coberturas abiertas
A167: DEC-080 | B167: Decidida | D167: Un gate que comprueba que los nombres entre capas existen
A168: DEC-079 | B168: Decidida | D168: La identidad fiscal del cliente tiene permiso propio, en dos roles
A169: DEC-078 | B169: Decidida | D169: El histórico fiscal del cliente está congelado
A170: DEC-077 | B170: Decidida | D170: Un contacto no cambia de cliente
A171: DEC-076 | B171: Decidida | D171: La lista de suites de restricción vive en un solo archivo
A172: DEC-075 | B172: Decidida | D172: El relevo del contacto principal se hace, no se rechaza
A173: DEC-074 | B173: Decidida | D173: Al dar de alta un cliente se crea su primera marca
A174: DEC-073 | B174: Decidida | D174: Un prospecto se apunta en cualquier país; activarlo exige cobertura | E174: ADOPTADA e implementada (2026-08-24, iteración 3.9)
A175: DEC-072 | B175: Decidida | D175: creator_addresses queda fuera de la regla de periodos
A176: DEC-071 | B176: Decidida | D176: Un perfil fiscal nuevo no puede empezar antes que el vigente
A177: DEC-070 | B177: Decidida | D177: Un bloqueo de agenda se registra aunque pise una campaña aceptada
A178: DEC-069 | B178: Decidida | D178: Las tarifas tienen permiso propio: creator.rate.manage | E178: ADOPTADA e implementada (2026-08-24, iteración 3.9)
A179: DEC-068 | B179: Decidida | D179: Cero es un precio válido, pero hay que declararlo | E179: ADOPTADA e implementada (2026-08-24, iteración 3.9)
A180: DEC-067 | B180: Decidida | D180: Los dos permisos de medios de pago van al rol finance | E180: ADOPTADA e implementada (2026-08-23, iteración 3.8)
A181: DEC-066 | B181: Decidida | D181: La cuenta de un medio de pago es inmutable: se sustituye, no se edita | E181: ADOPTADA e implementada (2026-08-23, iteración 3.8)
A182: DEC-065 | B182: Decidida | D182: La misma cuenta en dos creadores se marca, no se rechaza | E182: ADOPTADA e implementada (2026-08-23, iteración 3.8)
A183: DEC-064 | B183: Decidida | D183: El enfriamiento de un medio de pago son 24 horas, y es configuración | E183: ADOPTADA e implementada (2026-08-23, iteración 3.8)
A184: DEC-063 | B184: Decidida | D184: Los umbrales de coherencia son juicio, no verdad; y no rechazan nada | E184: ADOPTADA e implementada (2026-08-23, iteración 3.7) — umbrales revisables
A185: DEC-062 | B185: Decidida | D185: Los dos permisos fiscales van al mismo rol; la separación la impone la base | E185: ADOPTADA e implementada (2026-08-23, iteración 3.6)
A186: DEC-061 | B186: Decidida | D186: Las pruebas usan una base local y desechable, nunca la de desarrollo | E186: ADOPTADA e implementada (2026-08-23, iteración 3.5)
A187: DEC-060 | B187: Decidida | D187: Verificar y activar son permisos distintos, pero hoy el mismo rol | E187: ADOPTADA (2026-08-23, iteración 3.5) — decisión de negocio revisable
A188: DEC-059 | B188: Decidida | D188: Se acepta una versión de los términos, no una página | E188: ADOPTADA e implementada (2026-08-23, iteración 3.5)
A189: DEC-058 | B189: Decidida | D189: La identidad verificada es evidencia, no una casilla | E189: ADOPTADA e implementada (2026-08-23, iteración 3.5)
... A191: DEC-056 | B191: Decidida | D191: La bitácora se ordena por id, no por fecha, y redacta lo sensible | E191: ADOPTADA e implementada (2026-08-22, iteración 3.3)
A192: DEC-055 | B192: Decidida | D192: La primera pantalla de escritura no toca la identidad | E192: ADOPTADA e implementada (2026-08-22, iteración 3.2) | F192: — Primera pantalla del proyecto que escribe: edición de creador.
A193: DEC-054 | B193: Decidida | D193: La bitácora es inmutable en la base, no por convención | E193: ADOPTADA e implementada (2026-08-22, iteración 3.2) | F193: — audit_logs existía desde 2.4 y nadie escribía en ella. Al ir a llenarla apareció el segundo problema: la tabla admitía UPDATE y DELETE como cualquier otra.
A194: DEC-053 | B194: Decidida | D194: Autorización por permiso, sin atajo para el administrador | E194: ADOPTADA e implementada (2026-08-22, iteración 3.1)
A195: DEC-052 | B195: Decidida | D195: MySQL no admite subconsultas sobre la tabla que se está modificando | E195: ADOPTADA (2026-08-22)
A196: DEC-051 | B196: Decidida | D196: El CI corre la suite contra los dos motores, no contra uno | E196: ADOPTADA (2026-08-22). Recordatorio: tools/github-workflow-ci.yml sigue pendiente de mover a .github/workflows/ci.yml a mano — es ruta protegida | F196: — El CI validaba formato, análisis estático, fronteras entre módulos, migraciones y pruebas. Nada de eso comprueba que las restricciones se apliquen en el motor de producción, que no aplica CHECK.
A197: DEC-050 | B197: Decidida | D197: Las migraciones se contrastan contra el esquema de referencia, no se confía en que coincidan | E197: ADOPTADA e implementada (2026-08-22)
A198: DEC-049 | B198: Decidida | D198: Sin datos fiscales no hay alta, pero acompañamos a formalizarse | E198: ADOPTADA (2026-08-22) | F198: — Respuesta a Q-45. La propuesta inicial era pagar a un familiar del creador con declaración jurada de parentesco. El análisis de docs/fase-2/2.14-PAGO-A-TERCEROS.md identificó tres problemas: el comprobante deja de coincidir con el pago (riesgo de gasto reparable para la empresa que paga), señales de alerta de prevención de lavado, y contradicción con BR-FIN-003, que ya está implementada.
A199: DEC-048 | B199: Decidida | D199: La retención tiene tres estados, no dos | E199: ADOPTADA e implementada (2026-08-22, iteración 2.15) | F199: — Sobre Q-40 se decidió «que el modelo lo deje configurable». Al implementarlo apareció que el riesgo que yo había señalado —*«alguien pone un número a ojo y nadie se entera»*— ya estaba dentro del modelo, y era peor.
A200: DEC-047 | B200: Decidida | D200: Se factura a todos los países desde Perú | E200: ADOPTADA e implementada (2026-08-22) | F200: — Respuesta a Q-42. En lugar de constituir sociedad en cada país, se emiten todos los comprobantes desde la sociedad peruana. Los países se resuelven uno a uno más adelante.
A201: DEC-046 | B201: Decidida | D201: La base impone lo que ve en una fila; el resto lo impone el repositorio | E201: ADOPTADA (2026-08-22, iteración 2.13) | F201: — Cinco invariantes de finanzas son de varias filas o varias tablas (suma de líneas = subtotal, cobros ≤ total facturado, moneda de asiento = moneda de su payout, signo de una reversión, saldo no negativo). Ningún CHECK puede expresarlas.
A202: DEC-045 | B202: Decidida | D202: La inmutabilidad financiera se impone con disparadores, no con convención | E202: ADOPTADA e implementada (2026-08-22, iteración 2.13) | F202: — BR-FIN-008 («ningún registro financiero se elimina físicamente») y BR-FIN-002 («una corrección es un asiento de reversión») eran hasta ahora reglas de la capa de aplicación.
A203: DEC-044 | B203: Decidida | D203: Todo pago pertenece a un lote (no existen pagos sueltos) | E203: ADOPTADA e implementada (2026-08-22, iteración 2.13) | F203: — La primera versión de payouts permitía payout_batch_id NULL, pensando en el pago puntual fuera de la corrida quincenal.
A204: DEC-043 | B204: Decidida | D204: Dónde vive la base de datos de desarrollo | E204: ACORDADA en su intención; el motor concreto depende de DEC-042 | F204: C. Es lo que hace un equipo profesional y no cuesta más que A: el motor local se instala una vez. El bucle interno —migrar, probar, deshacer, repetir— tiene que ser rápido o se deja de ejecutar, y unas pruebas que tardan minutos son unas pruebas que nadie corre. La base remota es el ensayo general, no el banco de trabajo. — Se propone usar el mismo servidor que producción, con dos bases separadas: una de desarrollo y otra de producción. No es trabajar contra los datos reales; es usar el mismo motor. Ya hay otras aplicaciones Laravel funcionando en ese servidor sin incidencias.
A205: DEC-042 | B205: Decidida | D205: 🔴 El servidor es MySQL 5.7 y no aplica los CHECK *(confirmado empíricamente)* | E205: 🔴 CONFIRMADA — pendiente de elegir entre B y C | F205: — El servidor de la aplicación es Percona Server 5.7.44-48 sobre cPanel. La base de desarrollo (..._dev) y la de producción viven en él. docs/03 asumía MySQL 8.
A206: DEC-041 | B206: Propuesta | D206: Gamificación y Creator Score no se fusionan | E206: PROPUESTA | F206: B. El Score es interno, puede bajar y sirve para decidir a quién invitar; el XP es externo, nunca baja y sirve para motivar. Un creador que incumplió una vez debe bajar en el score y conservar el XP que ganó antes. — Ambos calculan un número sobre un creador a partir de los mismos eventos. La tentación de unirlos es enorme.
A207: DEC-040 | B207: Propuesta | D207: Referidos con consolidación diferida | E207: PROPUESTA | F207: B, más topes por periodo y verificación de que referente y referido no comparten documento, teléfono ni medio de pago. El vínculo se conserva siempre aunque el XP no se consolide: es dato de negocio. — Un programa de referidos con recompensa es, sin excepción, un imán de fraude: autorreferidos, cuentas falsas, granjas.
A208: DEC-039 | B208: Propuesta | D208: Los retos internos llevan siempre recompensa tangible 🔴 | E208: PROPUESTA | F208: B, sin excepción. El XP es el envoltorio y el reconocimiento; nunca el pago. Es la salvaguarda que la propia especificación anticipó en §16. — "Minicampañas de XP por hacer vídeos para la plataforma". Leído desde el otro lado, puede sonar a *"produce contenido de marketing para mi empresa y te pago con puntos"* — a creadores que ya producen por dinero para tus clientes. En una red pequeña, ese daño reputacional se propaga en un grupo de WhatsApp.
A209: DEC-038 | B209: Propuesta | D209: Ranking por cohortes, sin tabla global | E209: PROPUESTA | F209: C. Los puntos de liga se reinician por temporada; el XP nunca. Sin ranking público por ingresos, jamás. Un ranking global solo tiene sentido en una vista interna, y ahí es un reporte, no gamificación. — Una clasificación global con 1.000 creadores significa que 990 abren la app y ven que están perdiendo. Y con el tiempo se estanca: quien lleva más tiempo acumula más.
... A247: DEC-000 | B247: Decidida | D247: Nombre del producto y dominio ✅ RESUELTA | E247: ✅ APROBADA (addendum 2026-08-21) | F247: El addendum del 2026-08-21 lo define: la marca de plataforma es LATAM Social. El identificador técnico del proyecto pasa a latam-social. El nombre de trabajo provisional "CTS Creators" queda descartado. — El repositorio se llama ManageCampaingInfluencer (con error ortográfico). El nombre afecta marca, dominio, correos y branding.
